Workbook

Sheet Read me
A1: OptimalEcospace Live Solver: crowdsourced scenario programme
A3: Purpose | B3: A shared, factorial set of Live Solver sessions for the northern Gulf of Mexico (NGoM) Ecospace model. Each row of the Scenarios sheet is one Live Solver session (100 random layouts plus the status quo). Run by many people on their own computers, the sessions add up to a consistent dataset that can be pooled and compared: where to install reef, how much to spend, what decommissioning does, and how sensitive the answers are to uncertain inputs.
A4: Software | B4: Live Solver download (always the current version): https://github.com/mattwoodstock/OptimalEcospace/releases/download/live-solver/OptimalEcospace-LiveSolver.zip Requires R (with RStudio) and the Ecospace console (EwEClientConsole.exe). See the User Guide (docs/LiveSolver_User_Guide.docx) for installation.
A5: Required version | B5: The first line of the solver log must read 'Live Solver version ebf8874 (built ...)'. The coordinator will announce any change of version here; all scenarios in one analysis must use the same version.
A6: Scenario files | B6: Each scenario has a small configuration file (column 'Config file' on the Scenarios sheet) that holds only the settings that differ from the defaults. Load it in Setup > Save / load configuration > Load configuration; everything else is reset to the defaults, so a previously loaded scenario cannot leak into the next. The files are in the folder 'configs' delivered with this workbook.
A7: How to take part | B7: 1. Read the General rules sheet. 2. On the Scenarios sheet, pick an unclaimed row (Priority 1 first), enter your name in 'Assigned to' and set Status to 'Claimed'. 3. Run it (General rules 6-14). 4. Upload the zipped session folder and complete the row (General rules 15-18; checklist on the Submission & QC sheet).
A8: Design | B8: Four blocks: A, installation (full factorial, 144 scenarios); B, decommissioning (full factorial, 72); C, mixed install + decommission (full factorial, 36); D, sensitivity and replicates around a reference scenario (26). Factor levels and their sources are on the Factors & levels sheet; settings that never change are on Fixed settings.
A9: Priorities | B9: 1 = core comparisons over the whole model area plus the reference replicates (48 scenarios); 2 = whole-area variants and Alabama/Florida standard-module scenarios (103); 3 = remaining zone combinations and minor sensitivities (127). Finish all Priority 1 rows before starting Priority 2.
A10: Objectives | B10: All sessions use the four default objectives (red snapper biomass and catch, other managed reef fish biomass, fishery revenue; weight 1). Alternative objective weightings (Objective sets sheet) are applied afterwards by re-scoring the saved outputs, so they need no extra Ecospace runs.
A11: Pre-checked | B11: Every configuration file was loaded into the Live Solver and checked against the NGoM model in test mode: all 278 load, every one has eligible cells, and sampled layouts are feasible. 'Eligible cells' on the Scenarios sheet is what your Constraint preview must show after loading.
A13: Planning inputs
A14: Minutes per Ecospace run | B14: Typical 1-3.5 min on a desktop PC; enter your team's average. Used for the hour estimates. | C14: 2.5
A15: Total runs in the programme | C15: =SUM(Scenarios!T:T)+COUNTA(Scenarios!A:A)-1
A16: Total compute hours | C16: =ROUND(C15*'Read me'!$C$14/60,0)
A17: Hours per person (enter team size) | B17: Team size: | C17: 10
B18: Hours each: | C18: =ROUND(C15*'Read me'!$C$14/60/C17,0)

Sheet General rules
A1: No. | B1: Area | C1: Rule | D1: Why
A3: 1 | B3: Software | C3: Use the official download only (https://github.com/mattwoodstock/OptimalEcospace/releases/download/live-solver/OptimalEcospace-LiveSolver.zip). Confirm the first log line reads 'Live Solver version ebf8874'. Never edit any file in the package: the model (.eweaccdb), anything in Inputs, or the R code. | D3: Every contributor must simulate exactly the same model; a single edited map or parameter makes results impossible to pool.
A4: 2 | B4: Software | C4: Use the Ecospace console version installed at the default location (EcoSpace Console 1.4.3.1 64-bit). Record the console version in the Notes if it differs. | D4: Different console builds can produce different outputs.
A5: 3 | B5: Software | C5: Unzip a fresh copy of the package for each new programme version. One session at a time per unzipped folder; to run two sessions at once on one computer, use two separate unzipped folders. | D5: A session overwrites the map files in its own Inputs folder; two sessions in one folder would corrupt each other (the app blocks this with a lock file).
A6: 4 | B6: Claiming | C6: Before starting, enter your name in 'Assigned to' and set Status to 'Claimed' (then 'Running'). Do not run a row someone else has claimed. Work through Priority 1 first, then 2, then 3. | D6: Avoids duplicated work and ensures the core comparisons finish first.
A7: 5 | B7: Claiming | C7: Release a claim you cannot finish within 7 days (clear your name, Status 'Not started'). | D7: Keeps the programme moving.
A8: 6 | B8: Setup | C8: Start the app, open Setup, then Save / load configuration > Load configuration and choose the scenario's file from the 'configs' folder. Do not change any setting afterwards, with two exceptions: the console location and 'Threads' (performance only; record it). | D8: The configuration file is the scenario definition; manual edits create unrecorded variants.
A9: 7 | B9: Setup | C9: After loading, open the Constraint preview and check that the number of eligible cells (installation and/or decommissioning) equals 'Eligible install cells' / 'Eligible removal cells' on the Scenarios sheet. If it does not, stop and report. | D9: Confirms that the configuration loaded fully and that your copy of the model and maps is identical.
A10: 8 | B10: Setup | C10: Test mode must be OFF. The Model & run settings (Ecosim/Ecospace scenario 1, 30 years, 5-year spin-up, 12 time steps per year) must stay as loaded. | D10: Test mode produces made-up scores; run length and timing define when reef enters the model (year 10).
A11: 9 | B11: Setup | C11: Keep the default objectives (RS_Biomass, RS_Catch, Reef_Fish_Biomass, Total_Revenue, weight 1, maximise) and the default economics. Do not press Re-score with different objectives before submitting. | D11: A common scoring basis; other weightings are applied centrally afterwards (Objective sets sheet).
A12: 10 | B12: Running | C12: Run the number of scenarios listed (column 'Runs': 100 random layouts; 150 for the evolutionary-search scenario) with the listed random seed. Do not use 'Add iterations'. | D12: Equal sample sizes and fixed seeds make sessions comparable and reproducible.
A13: 11 | B13: Running | C13: Keep the computer plugged in and set it never to sleep or hibernate while a session runs. Closing the browser tab is fine; closing R or RStudio stops the session. | D13: The session lives in the R process; sleep or shutdown kills the Ecospace console mid-run.
A14: 12 | B14: Running | C14: Do not open the model in EwE desktop, edit files in Inputs, or run other heavy jobs while a session runs. | D14: Opening the model locks the database; heavy jobs slow runs and can trigger timeouts.
... A22: 20 | B22: Data | C22: Results are shared within the team for the joint analysis. Do not publish individual scenario results separately without the coordinator's agreement. | D22: Avoids conflicting partial analyses.

Sheet Scenarios
A1: Scenario ID | B1: Block | C1: Priority | D1: Strategy | E1: Code | F1: Description | G1: Zone | H1: Depth band | I1: Module type | J1: Layout | K1: Budget band | L1: Selection | M1: Removal | N1: Freed area becomes | O1: Removal count | P1: Shared budget | Q1: Sensitivity factor | R1: Settings to load / check (Setup panel > field: value) | S1: Config file | T1: Runs | U1: Seed | V1: Eligible install cells | W1: Eligible removal cells | X1: Est. hours | Y1: Assigned to | Z1: Status | AA1: Date started | AB1: Date finished | AC1: Version (from log) | AD1: Runs finished | AE1: Minutes per run | AF1: Threads | AG1: Computer (CPU) | AH1: Status quo RS_Biomass | AI1: Status quo RS_Catch | AJ1: QC | AK1: Upload link | AL1: Notes
A2: A001 | B2: A | C2: 1 | D2: Install | E2: INST-Region-Any-Std-Disp-Small | F2: Install standard prefab modules, dispersed, any eligible depth (10-100 m), Whole model area, small budget ($0.1-1 M) | G2: Whole model area | H2: Any eligible depth (10-100 m) | I2: Standard prefab module ($2,500; 6 m2; 3 m tall) | J2: Dispersed (no connectivity preference) | K2: Small: $0.1-1 M | R2: Strategy > Strategy: Install new structures Installation > Maximum budget per scenario (USD): 1,000,000 Installation > Minimum budget per scenario (USD): 100,000 Installation > How budgets are drawn: Uniform Installation > Favour cells next to existing modules: unticked Live solver / Search > Number of scenarios to run: 100 Search > Search algorithm: Random search Search > Random seed: 1,001 | S2: A001_INST-Region-Any-Std-Disp-Small.json | T2: 100 | U2: 1001 | V2: 988 | X2: =ROUND((T2+1)*'Read me'!$C$14/60,1) | Z2: Not started | AJ2: =IF(OR(AH2="",'Submission & QC'!$C$18=""),"",IF(AND(ABS(AH2-'Submission & QC'!$C$18)<=0.0005*ABS('Submission & QC'!$C$18),ABS(AI2-'Submission & QC'!$C$19)<=0.0005*ABS('Submission & QC'!$C$19)),"Pass","Fail"))
A3: A002 | B3: A | C3: 1 | D3: Install | E3: INST-Region-Any-Std-Disp-Medium | F3: Install standard prefab modules, dispersed, any eligible depth (10-100 m), Whole model area, medium budget ($1-5 M) | G3: Whole model area | H3: Any eligible depth (10-100 m) | I3: Standard prefab module ($2,500; 6 m2; 3 m tall) | J3: Dispersed (no connectivity preference) | K3: Medium: $1-5 M | R3: Strategy > Strategy: Install new structures Installation > Maximum budget per scenario (USD): 5,000,000 Installation > Minimum budget per scenario (USD): 1,000,000 Installation > How budgets are drawn: Uniform Installation > Favour cells next to existing modules: unticked Live solver / Search > Number of scenarios to run: 100 Search > Search algorithm: Random search Search > Random seed: 1,002 | S3: A002_INST-Region-Any-Std-Disp-Medium.json | T3: 100 | U3: 1002 | V3: 988 | X3: =ROUND((T3+1)*'Read me'!$C$14/60,1) | Z3: Not started | AJ3: =IF(OR(AH3="",'Submission & QC'!$C$18=""),"",IF(AND(ABS(AH3-'Submission & QC'!$C$18)<=0.0005*ABS('Submission & QC'!$C$18),ABS(AI3-'Submission & QC'!$C$19)<=0.0005*ABS('Submission & QC'!$C$19)),"Pass","Fail"))
A4: A003 | B4: A | C4: 1 | D4: Install | E4: INST-Region-Any-Std-Disp-Large | F4: Install standard prefab modules, dispersed, any eligible depth (10-100 m), Whole model area, large budget ($5-15 M) | G4: Whole model area | H4: Any eligible depth (10-100 m) | I4: Standard prefab module ($2,500; 6 m2; 3 m tall) | J4: Dispersed (no connectivity preference) | K4: Large: $5-15 M | R4: Strategy > Strategy: Install new structures Installation > Maximum budget per scenario (USD): 15,000,000 Installation > Minimum budget per scenario (USD): 5,000,000 Installation > How budgets are drawn: Uniform Installation > Favour cells next to existing modules: unticked Live solver / Search > Number of scenarios to run: 100 Search > Search algorithm: Random search Search > Random seed: 1,003 | S4: A003_INST-Region-Any-Std-Disp-Large.json | T4: 100 | U4: 1003 | V4: 988 | X4: =ROUND((T4+1)*'Read me'!$C$14/60,1) | Z4: Not started | AJ4: =IF(OR(AH4="",'Submission & QC'!$C$18=""),"",IF(AND(ABS(AH4-'Submission & QC'!$C$18)<=0.0005*ABS('Submission & QC'!$C$18),ABS(AI4-'Submission & QC'!$C$19)<=0.0005*ABS('Submission & QC'!$C$19)),"Pass","Fail"))
A5: A004 | B5: A | C5: 1 | D5: Install | E5: INST-Region-Any-Std-Clust-Small | F5: Install standard prefab modules, clustered, any eligible depth (10-100 m), Whole model area, small budget ($0.1-1 M) | G5: Whole model area | H5: Any eligible depth (10-100 m) | I5: Standard prefab module ($2,500; 6 m2; 3 m tall) | J5: Clustered (favour cells next to existing modules) | K5: Small: $0.1-1 M | R5: Strategy > Strategy: Install new structures Installation > Maximum budget per scenario (USD): 1,000,000 Installation > Minimum budget per scenario (USD): 100,000 Installation > How budgets are drawn: Uniform Installation > Favour cells next to existing modules: ticked Installation > Connectivity bonus: 10 Live solver / Search > Number of scenarios to run: 100 Search > Search algorithm: Random search Search > Random seed: 1,004 | S5: A004_INST-Region-Any-Std-Clust-Small.json | T5: 100 | U5: 1004 | V5: 988 | X5: =ROUND((T5+1)*'Read me'!$C$14/60,1) | Z5: Not started | AJ5: =IF(OR(AH5="",'Submission & QC'!$C$18=""),"",IF(AND(ABS(AH5-'Submission & QC'!$C$18)<=0.0005*ABS('Submission & QC'!$C$18),ABS(AI5-'Submission & QC'!$C$19)<=0.0005*ABS('Submission & QC'!$C$19)),"Pass","Fail"))
A6: A005 | B6: A | C6: 1 | D6: Install | E6: INST-Region-Any-Std-Clust-Medium | F6: Install standard prefab modules, clustered, any eligible depth (10-100 m), Whole model area, medium budget ($1-5 M) | G6: Whole model area | H6: Any eligible depth (10-100 m) | I6: Standard prefab module ($2,500; 6 m2; 3 m tall) | J6: Clustered (favour cells next to existing modules) | K6: Medium: $1-5 M | R6: Strategy > Strategy: Install new structures Installation > Maximum budget per scenario (USD): 5,000,000 Installation > Minimum budget per scenario (USD): 1,000,000 Installation > How budgets are drawn: Uniform Installation > Favour cells next to existing modules: ticked Installation > Connectivity bonus: 10 Live solver / Search > Number of scenarios to run: 100 Search > Search algorithm: Random search Search > Random seed: 1,005 | S6: A005_INST-Region-Any-Std-Clust-Medium.json | T6: 100 | U6: 1005 | V6: 988 | X6: =ROUND((T6+1)*'Read me'!$C$14/60,1) | Z6: Not started | AJ6: =IF(OR(AH6="",'Submission & QC'!$C$18=""),"",IF(AND(ABS(AH6-'Submission & QC'!$C$18)<=0.0005*ABS('Submission & QC'!$C$18),ABS(AI6-'Submission & QC'!$C$19)<=0.0005*ABS('Submission & QC'!$C$19)),"Pass","Fail"))
A7: A006 | B7: A | C7: 1 | D7: Install | E7: INST-Region-Any-Std-Clust-Large | F7: Install standard prefab modules, clustered, any eligible depth (10-100 m), Whole model area, large budget ($5-15 M) | G7: Whole model area | H7: Any eligible depth (10-100 m) | I7: Standard prefab module ($2,500; 6 m2; 3 m tall) | J7: Clustered (favour cells next to existing modules) | K7: Large: $5-15 M | R7: Strategy > Strategy: Install new structures Installation > Maximum budget per scenario (USD): 15,000,000 Installation > Minimum budget per scenario (USD): 5,000,000 Installation > How budgets are drawn: Uniform Installation > Favour cells next to existing modules: ticked Installation > Connectivity bonus: 10 Live solver / Search > Number of scenarios to run: 100 Search > Search algorithm: Random search Search > Random seed: 1,006 | S7: A006_INST-Region-Any-Std-Clust-Large.json | T7: 100 | U7: 1006 | V7: 988 | X7: =ROUND((T7+1)*'Read me'!$C$14/60,1) | Z7: Not started | AJ7: =IF(OR(AH7="",'Submission & QC'!$C$18=""),"",IF(AND(ABS(AH7-'Submission & QC'!$C$18)<=0.0005*ABS('Submission & QC'!$C$18),ABS(AI7-'Submission & QC'!$C$19)<=0.0005*ABS('Submission & QC'!$C$19)),"Pass","Fail"))
A8: A007 | B8: A | C8: 2 | D8: Install | E8: INST-Region-Any-Large-Disp-Small | F8: Install large modules, dispersed, any eligible depth (10-100 m), Whole model area, small budget ($0.1-1 M) | G8: Whole model area | H8: Any eligible depth (10-100 m) | I8: Large module ($12,000; 20 m2; 6 m tall) | J8: Dispersed (no connectivity preference) | K8: Small: $0.1-1 M | R8: Strategy > Strategy: Install new structures Installation > Maximum budget per scenario (USD): 1,000,000 Installation > Minimum budget per scenario (USD): 100,000 Installation > How budgets are drawn: Uniform Installation > Cost per module (USD): 12,000 Installation > Footprint (m2): 20 Installation > Height (m): 6 Installation > Favour cells next to existing modules: unticked Live solver / Search > Number of scenarios to run: 100 Search > Search algorithm: Random search Search > Random seed: 1,007 | S8: A007_INST-Region-Any-Large-Disp-Small.json | T8: 100 | U8: 1007 | V8: 988 | X8: =ROUND((T8+1)*'Read me'!$C$14/60,1) | Z8: Not started | AJ8: =IF(OR(AH8="",'Submission & QC'!$C$18=""),"",IF(AND(ABS(AH8-'Submission & QC'!$C$18)<=0.0005*ABS('Submission & QC'!$C$18),ABS(AI8-'Submission & QC'!$C$19)<=0.0005*ABS('Submission & QC'!$C$19)),"Pass","Fail"))
A9: A008 | B9: A | C9: 2 | D9: Install | E9: INST-Region-Any-Large-Disp-Medium | F9: Install large modules, dispersed, any eligible depth (10-100 m), Whole model area, medium budget ($1-5 M) | G9: Whole model area | H9: Any eligible depth (10-100 m) | I9: Large module ($12,000; 20 m2; 6 m tall) | J9: Dispersed (no connectivity preference) | K9: Medium: $1-5 M | R9: Strategy > Strategy: Install new structures Installation > Maximum budget per scenario (USD): 5,000,000 Installation > Minimum budget per scenario (USD): 1,000,000 Installation > How budgets are drawn: Uniform Installation > Cost per module (USD): 12,000 Installation > Footprint (m2): 20 Installation > Height (m): 6 Installation > Favour cells next to existing modules: unticked Live solver / Search > Number of scenarios to run: 100 Search > Search algorithm: Random search Search > Random seed: 1,008 | S9: A008_INST-Region-Any-Large-Disp-Medium.json | T9: 100 | U9: 1008 | V9: 988 | X9: =ROUND((T9+1)*'Read me'!$C$14/60,1) | Z9: Not started | AJ9: =IF(OR(AH9="",'Submission & QC'!$C$18=""),"",IF(AND(ABS(AH9-'Submission & QC'!$C$18)<=0.0005*ABS('Submission & QC'!$C$18),ABS(AI9-'Submission & QC'!$C$19)<=0.0005*ABS('Submission & QC'!$C$19)),"Pass","Fail"))
A10: A009 | B10: A | C10: 2 | D10: Install | E10: INST-Region-Any-Large-Disp-Large | F10: Install large modules, dispersed, any eligible depth (10-100 m), Whole model area, large budget ($5-15 M) | G10: Whole model area | H10: Any eligible depth (10-100 m) | I10: Large module ($12,000; 20 m2; 6 m tall) | J10: Dispersed (no connectivity preference) | K10: Large: $5-15 M | R10: Strategy > Strategy: Install new structures Installation > Maximum budget per scenario (USD): 15,000,000 Installation > Minimum budget per scenario (USD): 5,000,000 Installation > How budgets are drawn: Uniform Installation > Cost per module (USD): 12,000 Installation > Footprint (m2): 20 Installation > Height (m): 6 Installation > Favour cells next to existing modules: unticked Live solver / Search > Number of scenarios to run: 100 Search > Search algorithm: Random search Search > Random seed: 1,009 | S10: A009_INST-Region-Any-Large-Disp-Large.json | T10: 100 | U10: 1009 | V10: 988 | X10: =ROUND((T10+1)*'Read me'!$C$14/60,1) | Z10: Not started | AJ10: =IF(OR(AH10="",'Submission & QC'!$C$18=""),"",IF(AND(ABS(AH10-'Submission & QC'!$C$18)<=0.0005*ABS('Submission & QC'!$C$18),ABS(AI10-'Submission & QC'!$C$19)<=0.0005*ABS('Submission & QC'!$C$19)),"Pass","Fail"))
A11: A010 | B11: A | C11: 2 | D11: Install | E11: INST-Region-Any-Large-Clust-Small | F11: Install large modules, clustered, any eligible depth (10-100 m), Whole model area, small budget ($0.1-1 M) | G11: Whole model area | H11: Any eligible depth (10-100 m) | I11: Large module ($12,000; 20 m2; 6 m tall) | J11: Clustered (favour cells next to existing modules) | K11: Small: $0.1-1 M | R11: Strategy > Strategy: Install new structures Installation > Maximum budget per scenario (USD): 1,000,000 Installation > Minimum budget per scenario (USD): 100,000 Installation > How budgets are drawn: Uniform Installation > Cost per module (USD): 12,000 Installation > Footprint (m2): 20 Installation > Height (m): 6 Installation > Favour cells next to existing modules: ticked Installation > Connectivity bonus: 10 Live solver / Search > Number of scenarios to run: 100 Search > Search algorithm: Random search Search > Random seed: 1,010 | S11: A010_INST-Region-Any-Large-Clust-Small.json | T11: 100 | U11: 1010 | V11: 988 | X11: =ROUND((T11+1)*'Read me'!$C$14/60,1) | Z11: Not started | AJ11: =IF(OR(AH11="",'Submission & QC'!$C$18=""),"",IF(AND(ABS(AH11-'Submission & QC'!$C$18)<=0.0005*ABS('Submission & QC'!$C$18),ABS(AI11-'Submission & QC'!$C$19)<=0.0005*ABS('Submission & QC'!$C$19)),"Pass","Fail"))
A12: A011 | B12: A | C12: 2 | D12: Install | E12: INST-Region-Any-Large-Clust-Medium | F12: Install large modules, clustered, any eligible depth (10-100 m), Whole model area, medium budget ($1-5 M) | G12: Whole model area | H12: Any eligible depth (10-100 m) | I12: Large module ($12,000; 20 m2; 6 m tall) | J12: Clustered (favour cells next to existing modules) | K12: Medium: $1-5 M | R12: Strategy > Strategy: Install new structures Installation > Maximum budget per scenario (USD): 5,000,000 Installation > Minimum budget per scenario (USD): 1,000,000 Installation > How budgets are drawn: Uniform Installation > Cost per module (USD): 12,000 Installation > Footprint (m2): 20 Installation > Height (m): 6 Installation > Favour cells next to existing modules: ticked Installation > Connectivity bonus: 10 Live solver / Search > Number of scenarios to run: 100 Search > Search algorithm: Random search Search > Random seed: 1,011 | S12: A011_INST-Region-Any-Large-Clust-Medium.json | T12: 100 | U12: 1011 | V12: 988 | X12: =ROUND((T12+1)*'Read me'!$C$14/60,1) | Z12: Not started | AJ12: =IF(OR(AH12="",'Submission & QC'!$C$18=""),"",IF(AND(ABS(AH12-'Submission & QC'!$C$18)<=0.0005*ABS('Submission & QC'!$C$18),ABS(AI12-'Submission & QC'!$C$19)<=0.0005*ABS('Submission & QC'!$C$19)),"Pass","Fail"))
A13: A012 | B13: A | C13: 2 | D13: Install | E13: INST-Region-Any-Large-Clust-Large | F13: Install large modules, clustered, any eligible depth (10-100 m), Whole model area, large budget ($5-15 M) | G13: Whole model area | H13: Any eligible depth (10-100 m) | I13: Large module ($12,000; 20 m2; 6 m tall) | J13: Clustered (favour cells next to existing modules) | K13: Large: $5-15 M | R13: Strategy > Strategy: Install new structures Installation > Maximum budget per scenario (USD): 15,000,000 Installation > Minimum budget per scenario (USD): 5,000,000 Installation > How budgets are drawn: Uniform Installation > Cost per module (USD): 12,000 Installation > Footprint (m2): 20 Installation > Height (m): 6 Installation > Favour cells next to existing modules: ticked Installation > Connectivity bonus: 10 Live solver / Search > Number of scenarios to run: 100 Search > Search algorithm: Random search Search > Random seed: 1,012 | S13: A012_INST-Region-Any-Large-Clust-Large.json | T13: 100 | U13: 1012 | V13: 988 | X13: =ROUND((T13+1)*'Read me'!$C$14/60,1) | Z13: Not started | AJ13: =IF(OR(AH13="",'Submission & QC'!$C$18=""),"",IF(AND(ABS(AH13-'Submission & QC'!$C$18)<=0.0005*ABS('Submission & QC'!$C$18),ABS(AI13-'Submission & QC'!$C$19)<=0.0005*ABS('Submission & QC'!$C$19)),"Pass","Fail"))
... A145: A144 | B145: A | C145: 3 | D145: Install | E145: INST-FL-Deep-Large-Clust-Large | F145: Install large modules, clustered, deep (60-100 m), Florida panhandle (east of the Perdido River), large budget ($5-15 M) | G145: Florida panhandle (east of the Perdido River) | H145: Deep (60-100 m) | I145: Large module ($12,000; 20 m2; 6 m tall) | J145: Clustered (favour cells next to existing modules) | K145: Large: $5-15 M | R145: Strategy > Strategy: Install new structures Installation > Maximum budget per scenario (USD): 15,000,000 Installation > Minimum budget per scenario (USD): 5,000,000 Installation > How budgets are drawn: Uniform Installation > West lon: -87.51 Installation > Min depth (m): 60 Installation > Max depth (m): 100 Installation > Cost per module (USD): 12,000 Installation > Footprint (m2): 20 Installation > Height (m): 6 Installation > Favour cells next to existing modules: ticked Installation > Connectivity bonus: 10 Live solver / Search > Number of scenarios to run: 100 Search > Search algorithm: Random search Search > Random seed: 1,144 | S145: A144_INST-FL-Deep-Large-Clust-Large.json | T145: 100 | U145: 1144 | V145: 145 | X145: =ROUND((T145+1)*'Read me'!$C$14/60,1) | Z145: Not started | AJ145: =IF(OR(AH145="",'Submission & QC'!$C$18=""),"",IF(AND(ABS(AH145-'Submission & QC'!$C$18)<=0.0005*ABS('Submission & QC'!$C$18),ABS(AI145-'Submission & QC'!$C$19)<=0.0005*ABS('Submission & QC'!$C$19)),"Pass","Fail"))
A146: B145 | B146: B | C146: 1 | D146: Decommission | E146: DECOM-Region-Random-Full-Prop-Few | F146: Decommission: few: 1-10 removals, random first, full removal (100%; $50,000 + $1,000/m), freed area to natural habitats, proportionally, Whole model area | G146: Whole model area | L146: Random | M146: Full removal (100%; $50,000 + $1,000/m) | N146: Natural habitats, proportionally | O146: Few: 1-10 removals | R146: Strategy > Strategy: Decommission existing structures Decommissioning > Removal budget (USD): 10,000,000 Decommissioning > Cost: Depth-based Decommissioning > Fixed cost per removal (USD, added): 50,000 Decommissioning > USD per metre depth: 1,000 Decommissioning > Selection preference: Random Decommissioning > Freed area becomes: Natural habitats, proportionally Decommissioning > Min removals: 1 Decommissioning > Max removals: 10 Decommissioning > Fraction of each structure removed: 1.0 Live solver / Search > Number of scenarios to run: 100 Search > Search algorithm: Random search Search > Random seed: 1,145 | S146: B145_DECOM-Region-Random-Full-Prop-Few.json | T146: 100 | U146: 1145 | W146: 314 | X146: =ROUND((T146+1)*'Read me'!$C$14/60,1) | Z146: Not started | AJ146: =IF(OR(AH146="",'Submission & QC'!$C$18=""),"",IF(AND(ABS(AH146-'Submission & QC'!$C$18)<=0.0005*ABS('Submission & QC'!$C$18),ABS(AI146-'Submission & QC'!$C$19)<=0.0005*ABS('Submission & QC'!$C$19)),"Pass","Fail"))
A147: B146 | B147: B | C147: 1 | D147: Decommission | E147: DECOM-Region-Random-Full-Prop-Many | F147: Decommission: many: 11-50 removals, random first, full removal (100%; $50,000 + $1,000/m), freed area to natural habitats, proportionally, Whole model area | G147: Whole model area | L147: Random | M147: Full removal (100%; $50,000 + $1,000/m) | N147: Natural habitats, proportionally | O147: Many: 11-50 removals | R147: Strategy > Strategy: Decommission existing structures Decommissioning > Removal budget (USD): 10,000,000 Decommissioning > Cost: Depth-based Decommissioning > Fixed cost per removal (USD, added): 50,000 Decommissioning > USD per metre depth: 1,000 Decommissioning > Selection preference: Random Decommissioning > Freed area becomes: Natural habitats, proportionally Decommissioning > Min removals: 11 Decommissioning > Max removals: 50 Decommissioning > Fraction of each structure removed: 1.0 Live solver / Search > Number of scenarios to run: 100 Search > Search algorithm: Random search Search > Random seed: 1,146 | S147: B146_DECOM-Region-Random-Full-Prop-Many.json | T147: 100 | U147: 1146 | W147: 314 | X147: =ROUND((T147+1)*'Read me'!$C$14/60,1) | Z147: Not started | AJ147: =IF(OR(AH147="",'Submission & QC'!$C$18=""),"",IF(AND(ABS(AH147-'Submission & QC'!$C$18)<=0.0005*ABS('Submission & QC'!$C$18),ABS(AI147-'Submission & QC'!$C$19)<=0.0005*ABS('Submission & QC'!$C$19)),"Pass","Fail"))
A148: B147 | B148: B | C148: 2 | D148: Decommission | E148: DECOM-Region-Random-Full-Sand-Few | F148: Decommission: few: 1-10 removals, random first, full removal (100%; $50,000 + $1,000/m), freed area to sand, Whole model area | G148: Whole model area | L148: Random | M148: Full removal (100%; $50,000 + $1,000/m) | N148: Sand | O148: Few: 1-10 removals | R148: Strategy > Strategy: Decommission existing structures Decommissioning > Removal budget (USD): 10,000,000 Decommissioning > Cost: Depth-based Decommissioning > Fixed cost per removal (USD, added): 50,000 Decommissioning > USD per metre depth: 1,000 Decommissioning > Selection preference: Random Decommissioning > Freed area becomes: sand Decommissioning > Min removals: 1 Decommissioning > Max removals: 10 Decommissioning > Fraction of each structure removed: 1.0 Live solver / Search > Number of scenarios to run: 100 Search > Search algorithm: Random search Search > Random seed: 1,147 | S148: B147_DECOM-Region-Random-Full-Sand-Few.json | T148: 100 | U148: 1147 | W148: 314 | X148: =ROUND((T148+1)*'Read me'!$C$14/60,1) | Z148: Not started | AJ148: =IF(OR(AH148="",'Submission & QC'!$C$18=""),"",IF(AND(ABS(AH148-'Submission & QC'!$C$18)<=0.0005*ABS('Submission & QC'!$C$18),ABS(AI148-'Submission & QC'!$C$19)<=0.0005*ABS('Submission & QC'!$C$19)),"Pass","Fail"))
A149: B148 | B149: B | C149: 2 | D149: Decommission | E149: DECOM-Region-Random-Full-Sand-Many | F149: Decommission: many: 11-50 removals, random first, full removal (100%; $50,000 + $1,000/m), freed area to sand, Whole model area | G149: Whole model area | L149: Random | M149: Full removal (100%; $50,000 + $1,000/m) | N149: Sand | O149: Many: 11-50 removals | R149: Strategy > Strategy: Decommission existing structures Decommissioning > Removal budget (USD): 10,000,000 Decommissioning > Cost: Depth-based Decommissioning > Fixed cost per removal (USD, added): 50,000 Decommissioning > USD per metre depth: 1,000 Decommissioning > Selection preference: Random Decommissioning > Freed area becomes: sand Decommissioning > Min removals: 11 Decommissioning > Max removals: 50 Decommissioning > Fraction of each structure removed: 1.0 Live solver / Search > Number of scenarios to run: 100 Search > Search algorithm: Random search Search > Random seed: 1,148 | S149: B148_DECOM-Region-Random-Full-Sand-Many.json | T149: 100 | U149: 1148 | W149: 314 | X149: =ROUND((T149+1)*'Read me'!$C$14/60,1) | Z149: Not started | AJ149: =IF(OR(AH149="",'Submission & QC'!$C$18=""),"",IF(AND(ABS(AH149-'Submission & QC'!$C$18)<=0.0005*ABS('Submission & QC'!$C$18),ABS(AI149-'Submission & QC'!$C$19)<=0.0005*ABS('Submission & QC'!$C$19)),"Pass","Fail"))
A150: B149 | B150: B | C150: 1 | D150: Decommission | E150: DECOM-Region-Random-Partial-Prop-Few | F150: Decommission: few: 1-10 removals, random first, partial removal / toppling (50%; $30,000 + $600/m), freed area to natural habitats, proportionally, Whole model area | G150: Whole model area | L150: Random | M150: Partial removal / toppling (50%; $30,000 + $600/m) | N150: Natural habitats, proportionally | O150: Few: 1-10 removals | R150: Strategy > Strategy: Decommission existing structures Decommissioning > Removal budget (USD): 10,000,000 Decommissioning > Cost: Depth-based Decommissioning > Fixed cost per removal (USD, added): 30,000 Decommissioning > USD per metre depth: 600 Decommissioning > Selection preference: Random Decommissioning > Freed area becomes: Natural habitats, proportionally Decommissioning > Min removals: 1 Decommissioning > Max removals: 10 Decommissioning > Fraction of each structure removed: 0.5 Live solver / Search > Number of scenarios to run: 100 Search > Search algorithm: Random search Search > Random seed: 1,149 | S150: B149_DECOM-Region-Random-Partial-Prop-Few.json | T150: 100 | U150: 1149 | W150: 314 | X150: =ROUND((T150+1)*'Read me'!$C$14/60,1) | Z150: Not started | AJ150: =IF(OR(AH150="",'Submission & QC'!$C$18=""),"",IF(AND(ABS(AH150-'Submission & QC'!$C$18)<=0.0005*ABS('Submission & QC'!$C$18),ABS(AI150-'Submission & QC'!$C$19)<=0.0005*ABS('Submission & QC'!$C$19)),"Pass","Fail"))
A151: B150 | B151: B | C151: 1 | D151: Decommission | E151: DECOM-Region-Random-Partial-Prop-Many | F151: Decommission: many: 11-50 removals, random first, partial removal / toppling (50%; $30,000 + $600/m), freed area to natural habitats, proportionally, Whole model area | G151: Whole model area | L151: Random | M151: Partial removal / toppling (50%; $30,000 + $600/m) | N151: Natural habitats, proportionally | O151: Many: 11-50 removals | R151: Strategy > Strategy: Decommission existing structures Decommissioning > Removal budget (USD): 10,000,000 Decommissioning > Cost: Depth-based Decommissioning > Fixed cost per removal (USD, added): 30,000 Decommissioning > USD per metre depth: 600 Decommissioning > Selection preference: Random Decommissioning > Freed area becomes: Natural habitats, proportionally Decommissioning > Min removals: 11 Decommissioning > Max removals: 50 Decommissioning > Fraction of each structure removed: 0.5 Live solver / Search > Number of scenarios to run: 100 Search > Search algorithm: Random search Search > Random seed: 1,150 | S151: B150_DECOM-Region-Random-Partial-Prop-Many.json | T151: 100 | U151: 1150 | W151: 314 | X151: =ROUND((T151+1)*'Read me'!$C$14/60,1) | Z151: Not started | AJ151: =IF(OR(AH151="",'Submission & QC'!$C$18=""),"",IF(AND(ABS(AH151-'Submission & QC'!$C$18)<=0.0005*ABS('Submission & QC'!$C$18),ABS(AI151-'Submission & QC'!$C$19)<=0.0005*ABS('Submission & QC'!$C$19)),"Pass","Fail"))
A152: B151 | B152: B | C152: 2 | D152: Decommission | E152: DECOM-Region-Random-Partial-Sand-Few | F152: Decommission: few: 1-10 removals, random first, partial removal / toppling (50%; $30,000 + $600/m), freed area to sand, Whole model area | G152: Whole model area | L152: Random | M152: Partial removal / toppling (50%; $30,000 + $600/m) | N152: Sand | O152: Few: 1-10 removals | R152: Strategy > Strategy: Decommission existing structures Decommissioning > Removal budget (USD): 10,000,000 Decommissioning > Cost: Depth-based Decommissioning > Fixed cost per removal (USD, added): 30,000 Decommissioning > USD per metre depth: 600 Decommissioning > Selection preference: Random Decommissioning > Freed area becomes: sand Decommissioning > Min removals: 1 Decommissioning > Max removals: 10 Decommissioning > Fraction of each structure removed: 0.5 Live solver / Search > Number of scenarios to run: 100 Search > Search algorithm: Random search Search > Random seed: 1,151 | S152: B151_DECOM-Region-Random-Partial-Sand-Few.json | T152: 100 | U152: 1151 | W152: 314 | X152: =ROUND((T152+1)*'Read me'!$C$14/60,1) | Z152: Not started | AJ152: =IF(OR(AH152="",'Submission & QC'!$C$18=""),"",IF(AND(ABS(AH152-'Submission & QC'!$C$18)<=0.0005*ABS('Submission & QC'!$C$18),ABS(AI152-'Submission & QC'!$C$19)<=0.0005*ABS('Submission & QC'!$C$19)),"Pass","Fail"))
A153: B152 | B153: B | C153: 2 | D153: Decommission | E153: DECOM-Region-Random-Partial-Sand-Many | F153: Decommission: many: 11-50 removals, random first, partial removal / toppling (50%; $30,000 + $600/m), freed area to sand, Whole model area | G153: Whole model area | L153: Random | M153: Partial removal / toppling (50%; $30,000 + $600/m) | N153: Sand | O153: Many: 11-50 removals | R153: Strategy > Strategy: Decommission existing structures Decommissioning > Removal budget (USD): 10,000,000 Decommissioning > Cost: Depth-based Decommissioning > Fixed cost per removal (USD, added): 30,000 Decommissioning > USD per metre depth: 600 Decommissioning > Selection preference: Random Decommissioning > Freed area becomes: sand Decommissioning > Min removals: 11 Decommissioning > Max removals: 50 Decommissioning > Fraction of each structure removed: 0.5 Live solver / Search > Number of scenarios to run: 100 Search > Search algorithm: Random search Search > Random seed: 1,152 | S153: B152_DECOM-Region-Random-Partial-Sand-Many.json | T153: 100 | U153: 1152 | W153: 314 | X153: =ROUND((T153+1)*'Read me'!$C$14/60,1) | Z153: Not started | AJ153: =IF(OR(AH153="",'Submission & QC'!$C$18=""),"",IF(AND(ABS(AH153-'Submission & QC'!$C$18)<=0.0005*ABS('Submission & QC'!$C$18),ABS(AI153-'Submission & QC'!$C$19)<=0.0005*ABS('Submission & QC'!$C$19)),"Pass","Fail"))
A154: B153 | B154: B | C154: 1 | D154: Decommission | E154: DECOM-Region-Shallowest-Full-Prop-Few | F154: Decommission: few: 1-10 removals, shallowest first, full removal (100%; $50,000 + $1,000/m), freed area to natural habitats, proportionally, Whole model area | G154: Whole model area | L154: Shallowest | M154: Full removal (100%; $50,000 + $1,000/m) | N154: Natural habitats, proportionally | O154: Few: 1-10 removals | R154: Strategy > Strategy: Decommission existing structures Decommissioning > Removal budget (USD): 10,000,000 Decommissioning > Cost: Depth-based Decommissioning > Fixed cost per removal (USD, added): 50,000 Decommissioning > USD per metre depth: 1,000 Decommissioning > Selection preference: Prefer shallowest Decommissioning > Freed area becomes: Natural habitats, proportionally Decommissioning > Min removals: 1 Decommissioning > Max removals: 10 Decommissioning > Fraction of each structure removed: 1.0 Live solver / Search > Number of scenarios to run: 100 Search > Search algorithm: Random search Search > Random seed: 1,153 | S154: B153_DECOM-Region-Shallowest-Full-Prop-Few.json | T154: 100 | U154: 1153 | W154: 314 | X154: =ROUND((T154+1)*'Read me'!$C$14/60,1) | Z154: Not started | AJ154: =IF(OR(AH154="",'Submission & QC'!$C$18=""),"",IF(AND(ABS(AH154-'Submission & QC'!$C$18)<=0.0005*ABS('Submission & QC'!$C$18),ABS(AI154-'Submission & QC'!$C$19)<=0.0005*ABS('Submission & QC'!$C$19)),"Pass","Fail"))
A155: B154 | B155: B | C155: 1 | D155: Decommission | E155: DECOM-Region-Shallowest-Full-Prop-Many | F155: Decommission: many: 11-50 removals, shallowest first, full removal (100%; $50,000 + $1,000/m), freed area to natural habitats, proportionally, Whole model area | G155: Whole model area | L155: Shallowest | M155: Full removal (100%; $50,000 + $1,000/m) | N155: Natural habitats, proportionally | O155: Many: 11-50 removals | R155: Strategy > Strategy: Decommission existing structures Decommissioning > Removal budget (USD): 10,000,000 Decommissioning > Cost: Depth-based Decommissioning > Fixed cost per removal (USD, added): 50,000 Decommissioning > USD per metre depth: 1,000 Decommissioning > Selection preference: Prefer shallowest Decommissioning > Freed area becomes: Natural habitats, proportionally Decommissioning > Min removals: 11 Decommissioning > Max removals: 50 Decommissioning > Fraction of each structure removed: 1.0 Live solver / Search > Number of scenarios to run: 100 Search > Search algorithm: Random search Search > Random seed: 1,154 | S155: B154_DECOM-Region-Shallowest-Full-Prop-Many.json | T155: 100 | U155: 1154 | W155: 314 | X155: =ROUND((T155+1)*'Read me'!$C$14/60,1) | Z155: Not started | AJ155: =IF(OR(AH155="",'Submission & QC'!$C$18=""),"",IF(AND(ABS(AH155-'Submission & QC'!$C$18)<=0.0005*ABS('Submission & QC'!$C$18),ABS(AI155-'Submission & QC'!$C$19)<=0.0005*ABS('Submission & QC'!$C$19)),"Pass","Fail"))
A156: B155 | B156: B | C156: 2 | D156: Decommission | E156: DECOM-Region-Shallowest-Full-Sand-Few | F156: Decommission: few: 1-10 removals, shallowest first, full removal (100%; $50,000 + $1,000/m), freed area to sand, Whole model area | G156: Whole model area | L156: Shallowest | M156: Full removal (100%; $50,000 + $1,000/m) | N156: Sand | O156: Few: 1-10 removals | R156: Strategy > Strategy: Decommission existing structures Decommissioning > Removal budget (USD): 10,000,000 Decommissioning > Cost: Depth-based Decommissioning > Fixed cost per removal (USD, added): 50,000 Decommissioning > USD per metre depth: 1,000 Decommissioning > Selection preference: Prefer shallowest Decommissioning > Freed area becomes: sand Decommissioning > Min removals: 1 Decommissioning > Max removals: 10 Decommissioning > Fraction of each structure removed: 1.0 Live solver / Search > Number of scenarios to run: 100 Search > Search algorithm: Random search Search > Random seed: 1,155 | S156: B155_DECOM-Region-Shallowest-Full-Sand-Few.json | T156: 100 | U156: 1155 | W156: 314 | X156: =ROUND((T156+1)*'Read me'!$C$14/60,1) | Z156: Not started | AJ156: =IF(OR(AH156="",'Submission & QC'!$C$18=""),"",IF(AND(ABS(AH156-'Submission & QC'!$C$18)<=0.0005*ABS('Submission & QC'!$C$18),ABS(AI156-'Submission & QC'!$C$19)<=0.0005*ABS('Submission & QC'!$C$19)),"Pass","Fail"))
A157: B156 | B157: B | C157: 2 | D157: Decommission | E157: DECOM-Region-Shallowest-Full-Sand-Many | F157: Decommission: many: 11-50 removals, shallowest first, full removal (100%; $50,000 + $1,000/m), freed area to sand, Whole model area | G157: Whole model area | L157: Shallowest | M157: Full removal (100%; $50,000 + $1,000/m) | N157: Sand | O157: Many: 11-50 removals | R157: Strategy > Strategy: Decommission existing structures Decommissioning > Removal budget (USD): 10,000,000 Decommissioning > Cost: Depth-based Decommissioning > Fixed cost per removal (USD, added): 50,000 Decommissioning > USD per metre depth: 1,000 Decommissioning > Selection preference: Prefer shallowest Decommissioning > Freed area becomes: sand Decommissioning > Min removals: 11 Decommissioning > Max removals: 50 Decommissioning > Fraction of each structure removed: 1.0 Live solver / Search > Number of scenarios to run: 100 Search > Search algorithm: Random search Search > Random seed: 1,156 | S157: B156_DECOM-Region-Shallowest-Full-Sand-Many.json | T157: 100 | U157: 1156 | W157: 314 | X157: =ROUND((T157+1)*'Read me'!$C$14/60,1) | Z157: Not started | AJ157: =IF(OR(AH157="",'Submission & QC'!$C$18=""),"",IF(AND(ABS(AH157-'Submission & QC'!$C$18)<=0.0005*ABS('Submission & QC'!$C$18),ABS(AI157-'Submission & QC'!$C$19)<=0.0005*ABS('Submission & QC'!$C$19)),"Pass","Fail"))
... A217: B216 | B217: B | C217: 3 | D217: Decommission | E217: DECOM-FL-Deepest-Partial-Sand-Many | F217: Decommission: many: 11-50 removals, deepest first, partial removal / toppling (50%; $30,000 + $600/m), freed area to sand, Florida panhandle (east of the Perdido River) | G217: Florida panhandle (east of the Perdido River) | L217: Deepest | M217: Partial removal / toppling (50%; $30,000 + $600/m) | N217: Sand | O217: Many: 11-50 removals | R217: Strategy > Strategy: Decommission existing structures Decommissioning > Removal budget (USD): 10,000,000 Decommissioning > Cost: Depth-based Decommissioning > Fixed cost per removal (USD, added): 30,000 Decommissioning > USD per metre depth: 600 Decommissioning > West lon: -87.51 Decommissioning > Selection preference: Prefer deepest Decommissioning > Freed area becomes: sand Decommissioning > Min removals: 11 Decommissioning > Max removals: 50 Decommissioning > Fraction of each structure removed: 0.5 Live solver / Search > Number of scenarios to run: 100 Search > Search algorithm: Random search Search > Random seed: 1,216 | S217: B216_DECOM-FL-Deepest-Partial-Sand-Many.json | T217: 100 | U217: 1216 | W217: 118 | X217: =ROUND((T217+1)*'Read me'!$C$14/60,1) | Z217: Not started | AJ217: =IF(OR(AH217="",'Submission & QC'!$C$18=""),"",IF(AND(ABS(AH217-'Submission & QC'!$C$18)<=0.0005*ABS('Submission & QC'!$C$18),ABS(AI217-'Submission & QC'!$C$19)<=0.0005*ABS('Submission & QC'!$C$19)),"Pass","Fail"))
A218: C217 | B218: C | C218: 1 | D218: Mixed | E218: MIX-Region-Separate-Small-Full | F218: Mixed: install and remove (separate budgets), small install budget ($0.1-1 M), full removal (100%; $50,000 + $1,000/m), Whole model area | G218: Whole model area | K218: Small: $0.1-1 M | M218: Full removal (100%; $50,000 + $1,000/m) | P218: No | R218: Strategy > Strategy: Mixed: decommission and install Strategy > Shared budget: unticked Installation > Maximum budget per scenario (USD): 1,000,000 Installation > Minimum budget per scenario (USD): 100,000 Installation > How budgets are drawn: Uniform Decommissioning > Removal budget (USD): 5,000,000 Decommissioning > Cost: Depth-based Decommissioning > Fixed cost per removal (USD, added): 50,000 Decommissioning > USD per metre depth: 1,000 Decommissioning > Min removals: 1 Decommissioning > Max removals: 25 Decommissioning > Fraction of each structure removed: 1.0 Live solver / Search > Number of scenarios to run: 100 Search > Search algorithm: Random search Search > Random seed: 1,217 | S218: C217_MIX-Region-Separate-Small-Full.json | T218: 100 | U218: 1217 | V218: 988 | W218: 314 | X218: =ROUND((T218+1)*'Read me'!$C$14/60,1) | Z218: Not started | AJ218: =IF(OR(AH218="",'Submission & QC'!$C$18=""),"",IF(AND(ABS(AH218-'Submission & QC'!$C$18)<=0.0005*ABS('Submission & QC'!$C$18),ABS(AI218-'Submission & QC'!$C$19)<=0.0005*ABS('Submission & QC'!$C$19)),"Pass","Fail"))
A219: C218 | B219: C | C219: 2 | D219: Mixed | E219: MIX-Region-Separate-Small-Partial | F219: Mixed: install and remove (separate budgets), small install budget ($0.1-1 M), partial removal / toppling (50%; $30,000 + $600/m), Whole model area | G219: Whole model area | K219: Small: $0.1-1 M | M219: Partial removal / toppling (50%; $30,000 + $600/m) | P219: No | R219: Strategy > Strategy: Mixed: decommission and install Strategy > Shared budget: unticked Installation > Maximum budget per scenario (USD): 1,000,000 Installation > Minimum budget per scenario (USD): 100,000 Installation > How budgets are drawn: Uniform Decommissioning > Removal budget (USD): 5,000,000 Decommissioning > Cost: Depth-based Decommissioning > Fixed cost per removal (USD, added): 30,000 Decommissioning > USD per metre depth: 600 Decommissioning > Min removals: 1 Decommissioning > Max removals: 25 Decommissioning > Fraction of each structure removed: 0.5 Live solver / Search > Number of scenarios to run: 100 Search > Search algorithm: Random search Search > Random seed: 1,218 | S219: C218_MIX-Region-Separate-Small-Partial.json | T219: 100 | U219: 1218 | V219: 988 | W219: 314 | X219: =ROUND((T219+1)*'Read me'!$C$14/60,1) | Z219: Not started | AJ219: =IF(OR(AH219="",'Submission & QC'!$C$18=""),"",IF(AND(ABS(AH219-'Submission & QC'!$C$18)<=0.0005*ABS('Submission & QC'!$C$18),ABS(AI219-'Submission & QC'!$C$19)<=0.0005*ABS('Submission & QC'!$C$19)),"Pass","Fail"))
A220: C219 | B220: C | C220: 1 | D220: Mixed | E220: MIX-Region-Separate-Medium-Full | F220: Mixed: install and remove (separate budgets), medium install budget ($1-5 M), full removal (100%; $50,000 + $1,000/m), Whole model area | G220: Whole model area | K220: Medium: $1-5 M | M220: Full removal (100%; $50,000 + $1,000/m) | P220: No | R220: Strategy > Strategy: Mixed: decommission and install Strategy > Shared budget: unticked Installation > Maximum budget per scenario (USD): 5,000,000 Installation > Minimum budget per scenario (USD): 1,000,000 Installation > How budgets are drawn: Uniform Decommissioning > Removal budget (USD): 5,000,000 Decommissioning > Cost: Depth-based Decommissioning > Fixed cost per removal (USD, added): 50,000 Decommissioning > USD per metre depth: 1,000 Decommissioning > Min removals: 1 Decommissioning > Max removals: 25 Decommissioning > Fraction of each structure removed: 1.0 Live solver / Search > Number of scenarios to run: 100 Search > Search algorithm: Random search Search > Random seed: 1,219 | S220: C219_MIX-Region-Separate-Medium-Full.json | T220: 100 | U220: 1219 | V220: 988 | W220: 314 | X220: =ROUND((T220+1)*'Read me'!$C$14/60,1) | Z220: Not started | AJ220: =IF(OR(AH220="",'Submission & QC'!$C$18=""),"",IF(AND(ABS(AH220-'Submission & QC'!$C$18)<=0.0005*ABS('Submission & QC'!$C$18),ABS(AI220-'Submission & QC'!$C$19)<=0.0005*ABS('Submission & QC'!$C$19)),"Pass","Fail"))
A221: C220 | B221: C | C221: 2 | D221: Mixed | E221: MIX-Region-Separate-Medium-Partial | F221: Mixed: install and remove (separate budgets), medium install budget ($1-5 M), partial removal / toppling (50%; $30,000 + $600/m), Whole model area | G221: Whole model area | K221: Medium: $1-5 M | M221: Partial removal / toppling (50%; $30,000 + $600/m) | P221: No | R221: Strategy > Strategy: Mixed: decommission and install Strategy > Shared budget: unticked Installation > Maximum budget per scenario (USD): 5,000,000 Installation > Minimum budget per scenario (USD): 1,000,000 Installation > How budgets are drawn: Uniform Decommissioning > Removal budget (USD): 5,000,000 Decommissioning > Cost: Depth-based Decommissioning > Fixed cost per removal (USD, added): 30,000 Decommissioning > USD per metre depth: 600 Decommissioning > Min removals: 1 Decommissioning > Max removals: 25 Decommissioning > Fraction of each structure removed: 0.5 Live solver / Search > Number of scenarios to run: 100 Search > Search algorithm: Random search Search > Random seed: 1,220 | S221: C220_MIX-Region-Separate-Medium-Partial.json | T221: 100 | U221: 1220 | V221: 988 | W221: 314 | X221: =ROUND((T221+1)*'Read me'!$C$14/60,1) | Z221: Not started | AJ221: =IF(OR(AH221="",'Submission & QC'!$C$18=""),"",IF(AND(ABS(AH221-'Submission & QC'!$C$18)<=0.0005*ABS('Submission & QC'!$C$18),ABS(AI221-'Submission & QC'!$C$19)<=0.0005*ABS('Submission & QC'!$C$19)),"Pass","Fail"))
A222: C221 | B222: C | C222: 1 | D222: Mixed | E222: MIX-Region-Separate-Large-Full | F222: Mixed: install and remove (separate budgets), large install budget ($5-15 M), full removal (100%; $50,000 + $1,000/m), Whole model area | G222: Whole model area | K222: Large: $5-15 M | M222: Full removal (100%; $50,000 + $1,000/m) | P222: No | R222: Strategy > Strategy: Mixed: decommission and install Strategy > Shared budget: unticked Installation > Maximum budget per scenario (USD): 15,000,000 Installation > Minimum budget per scenario (USD): 5,000,000 Installation > How budgets are drawn: Uniform Decommissioning > Removal budget (USD): 5,000,000 Decommissioning > Cost: Depth-based Decommissioning > Fixed cost per removal (USD, added): 50,000 Decommissioning > USD per metre depth: 1,000 Decommissioning > Min removals: 1 Decommissioning > Max removals: 25 Decommissioning > Fraction of each structure removed: 1.0 Live solver / Search > Number of scenarios to run: 100 Search > Search algorithm: Random search Search > Random seed: 1,221 | S222: C221_MIX-Region-Separate-Large-Full.json | T222: 100 | U222: 1221 | V222: 988 | W222: 314 | X222: =ROUND((T222+1)*'Read me'!$C$14/60,1) | Z222: Not started | AJ222: =IF(OR(AH222="",'Submission & QC'!$C$18=""),"",IF(AND(ABS(AH222-'Submission & QC'!$C$18)<=0.0005*ABS('Submission & QC'!$C$18),ABS(AI222-'Submission & QC'!$C$19)<=0.0005*ABS('Submission & QC'!$C$19)),"Pass","Fail"))
A223: C222 | B223: C | C223: 2 | D223: Mixed | E223: MIX-Region-Separate-Large-Partial | F223: Mixed: install and remove (separate budgets), large install budget ($5-15 M), partial removal / toppling (50%; $30,000 + $600/m), Whole model area | G223: Whole model area | K223: Large: $5-15 M | M223: Partial removal / toppling (50%; $30,000 + $600/m) | P223: No | R223: Strategy > Strategy: Mixed: decommission and install Strategy > Shared budget: unticked Installation > Maximum budget per scenario (USD): 15,000,000 Installation > Minimum budget per scenario (USD): 5,000,000 Installation > How budgets are drawn: Uniform Decommissioning > Removal budget (USD): 5,000,000 Decommissioning > Cost: Depth-based Decommissioning > Fixed cost per removal (USD, added): 30,000 Decommissioning > USD per metre depth: 600 Decommissioning > Min removals: 1 Decommissioning > Max removals: 25 Decommissioning > Fraction of each structure removed: 0.5 Live solver / Search > Number of scenarios to run: 100 Search > Search algorithm: Random search Search > Random seed: 1,222 | S223: C222_MIX-Region-Separate-Large-Partial.json | T223: 100 | U223: 1222 | V223: 988 | W223: 314 | X223: =ROUND((T223+1)*'Read me'!$C$14/60,1) | Z223: Not started | AJ223: =IF(OR(AH223="",'Submission & QC'!$C$18=""),"",IF(AND(ABS(AH223-'Submission & QC'!$C$18)<=0.0005*ABS('Submission & QC'!$C$18),ABS(AI223-'Submission & QC'!$C$19)<=0.0005*ABS('Submission & QC'!$C$19)),"Pass","Fail"))
A224: C223 | B224: C | C224: 1 | D224: Mixed | E224: MIX-Region-Shared-Small-Full | F224: Mixed: install and remove (one shared budget), small install budget ($0.1-1 M), full removal (100%; $50,000 + $1,000/m), Whole model area | G224: Whole model area | K224: Small: $0.1-1 M | M224: Full removal (100%; $50,000 + $1,000/m) | P224: Yes | R224: Strategy > Strategy: Mixed: decommission and install Strategy > Shared budget: ticked Installation > Maximum budget per scenario (USD): 1,000,000 Installation > Minimum budget per scenario (USD): 100,000 Installation > How budgets are drawn: Uniform Decommissioning > Removal budget (USD): 5,000,000 Decommissioning > Cost: Depth-based Decommissioning > Fixed cost per removal (USD, added): 50,000 Decommissioning > USD per metre depth: 1,000 Decommissioning > Min removals: 1 Decommissioning > Max removals: 25 Decommissioning > Fraction of each structure removed: 1.0 Live solver / Search > Number of scenarios to run: 100 Search > Search algorithm: Random search Search > Random seed: 1,223 | S224: C223_MIX-Region-Shared-Small-Full.json | T224: 100 | U224: 1223 | V224: 988 | W224: 314 | X224: =ROUND((T224+1)*'Read me'!$C$14/60,1) | Z224: Not started | AJ224: =IF(OR(AH224="",'Submission & QC'!$C$18=""),"",IF(AND(ABS(AH224-'Submission & QC'!$C$18)<=0.0005*ABS('Submission & QC'!$C$18),ABS(AI224-'Submission & QC'!$C$19)<=0.0005*ABS('Submission & QC'!$C$19)),"Pass","Fail"))
A225: C224 | B225: C | C225: 2 | D225: Mixed | E225: MIX-Region-Shared-Small-Partial | F225: Mixed: install and remove (one shared budget), small install budget ($0.1-1 M), partial removal / toppling (50%; $30,000 + $600/m), Whole model area | G225: Whole model area | K225: Small: $0.1-1 M | M225: Partial removal / toppling (50%; $30,000 + $600/m) | P225: Yes | R225: Strategy > Strategy: Mixed: decommission and install Strategy > Shared budget: ticked Installation > Maximum budget per scenario (USD): 1,000,000 Installation > Minimum budget per scenario (USD): 100,000 Installation > How budgets are drawn: Uniform Decommissioning > Removal budget (USD): 5,000,000 Decommissioning > Cost: Depth-based Decommissioning > Fixed cost per removal (USD, added): 30,000 Decommissioning > USD per metre depth: 600 Decommissioning > Min removals: 1 Decommissioning > Max removals: 25 Decommissioning > Fraction of each structure removed: 0.5 Live solver / Search > Number of scenarios to run: 100 Search > Search algorithm: Random search Search > Random seed: 1,224 | S225: C224_MIX-Region-Shared-Small-Partial.json | T225: 100 | U225: 1224 | V225: 988 | W225: 314 | X225: =ROUND((T225+1)*'Read me'!$C$14/60,1) | Z225: Not started | AJ225: =IF(OR(AH225="",'Submission & QC'!$C$18=""),"",IF(AND(ABS(AH225-'Submission & QC'!$C$18)<=0.0005*ABS('Submission & QC'!$C$18),ABS(AI225-'Submission & QC'!$C$19)<=0.0005*ABS('Submission & QC'!$C$19)),"Pass","Fail"))
A226: C225 | B226: C | C226: 1 | D226: Mixed | E226: MIX-Region-Shared-Medium-Full | F226: Mixed: install and remove (one shared budget), medium install budget ($1-5 M), full removal (100%; $50,000 + $1,000/m), Whole model area | G226: Whole model area | K226: Medium: $1-5 M | M226: Full removal (100%; $50,000 + $1,000/m) | P226: Yes | R226: Strategy > Strategy: Mixed: decommission and install Strategy > Shared budget: ticked Installation > Maximum budget per scenario (USD): 5,000,000 Installation > Minimum budget per scenario (USD): 1,000,000 Installation > How budgets are drawn: Uniform Decommissioning > Removal budget (USD): 5,000,000 Decommissioning > Cost: Depth-based Decommissioning > Fixed cost per removal (USD, added): 50,000 Decommissioning > USD per metre depth: 1,000 Decommissioning > Min removals: 1 Decommissioning > Max removals: 25 Decommissioning > Fraction of each structure removed: 1.0 Live solver / Search > Number of scenarios to run: 100 Search > Search algorithm: Random search Search > Random seed: 1,225 | S226: C225_MIX-Region-Shared-Medium-Full.json | T226: 100 | U226: 1225 | V226: 988 | W226: 314 | X226: =ROUND((T226+1)*'Read me'!$C$14/60,1) | Z226: Not started | AJ226: =IF(OR(AH226="",'Submission & QC'!$C$18=""),"",IF(AND(ABS(AH226-'Submission & QC'!$C$18)<=0.0005*ABS('Submission & QC'!$C$18),ABS(AI226-'Submission & QC'!$C$19)<=0.0005*ABS('Submission & QC'!$C$19)),"Pass","Fail"))
A227: C226 | B227: C | C227: 2 | D227: Mixed | E227: MIX-Region-Shared-Medium-Partial | F227: Mixed: install and remove (one shared budget), medium install budget ($1-5 M), partial removal / toppling (50%; $30,000 + $600/m), Whole model area | G227: Whole model area | K227: Medium: $1-5 M | M227: Partial removal / toppling (50%; $30,000 + $600/m) | P227: Yes | R227: Strategy > Strategy: Mixed: decommission and install Strategy > Shared budget: ticked Installation > Maximum budget per scenario (USD): 5,000,000 Installation > Minimum budget per scenario (USD): 1,000,000 Installation > How budgets are drawn: Uniform Decommissioning > Removal budget (USD): 5,000,000 Decommissioning > Cost: Depth-based Decommissioning > Fixed cost per removal (USD, added): 30,000 Decommissioning > USD per metre depth: 600 Decommissioning > Min removals: 1 Decommissioning > Max removals: 25 Decommissioning > Fraction of each structure removed: 0.5 Live solver / Search > Number of scenarios to run: 100 Search > Search algorithm: Random search Search > Random seed: 1,226 | S227: C226_MIX-Region-Shared-Medium-Partial.json | T227: 100 | U227: 1226 | V227: 988 | W227: 314 | X227: =ROUND((T227+1)*'Read me'!$C$14/60,1) | Z227: Not started | AJ227: =IF(OR(AH227="",'Submission & QC'!$C$18=""),"",IF(AND(ABS(AH227-'Submission & QC'!$C$18)<=0.0005*ABS('Submission & QC'!$C$18),ABS(AI227-'Submission & QC'!$C$19)<=0.0005*ABS('Submission & QC'!$C$19)),"Pass","Fail"))
A228: C227 | B228: C | C228: 1 | D228: Mixed | E228: MIX-Region-Shared-Large-Full | F228: Mixed: install and remove (one shared budget), large install budget ($5-15 M), full removal (100%; $50,000 + $1,000/m), Whole model area | G228: Whole model area | K228: Large: $5-15 M | M228: Full removal (100%; $50,000 + $1,000/m) | P228: Yes | R228: Strategy > Strategy: Mixed: decommission and install Strategy > Shared budget: ticked Installation > Maximum budget per scenario (USD): 15,000,000 Installation > Minimum budget per scenario (USD): 5,000,000 Installation > How budgets are drawn: Uniform Decommissioning > Removal budget (USD): 5,000,000 Decommissioning > Cost: Depth-based Decommissioning > Fixed cost per removal (USD, added): 50,000 Decommissioning > USD per metre depth: 1,000 Decommissioning > Min removals: 1 Decommissioning > Max removals: 25 Decommissioning > Fraction of each structure removed: 1.0 Live solver / Search > Number of scenarios to run: 100 Search > Search algorithm: Random search Search > Random seed: 1,227 | S228: C227_MIX-Region-Shared-Large-Full.json | T228: 100 | U228: 1227 | V228: 988 | W228: 314 | X228: =ROUND((T228+1)*'Read me'!$C$14/60,1) | Z228: Not started | AJ228: =IF(OR(AH228="",'Submission & QC'!$C$18=""),"",IF(AND(ABS(AH228-'Submission & QC'!$C$18)<=0.0005*ABS('Submission & QC'!$C$18),ABS(AI228-'Submission & QC'!$C$19)<=0.0005*ABS('Submission & QC'!$C$19)),"Pass","Fail"))
A229: C228 | B229: C | C229: 2 | D229: Mixed | E229: MIX-Region-Shared-Large-Partial | F229: Mixed: install and remove (one shared budget), large install budget ($5-15 M), partial removal / toppling (50%; $30,000 + $600/m), Whole model area | G229: Whole model area | K229: Large: $5-15 M | M229: Partial removal / toppling (50%; $30,000 + $600/m) | P229: Yes | R229: Strategy > Strategy: Mixed: decommission and install Strategy > Shared budget: ticked Installation > Maximum budget per scenario (USD): 15,000,000 Installation > Minimum budget per scenario (USD): 5,000,000 Installation > How budgets are drawn: Uniform Decommissioning > Removal budget (USD): 5,000,000 Decommissioning > Cost: Depth-based Decommissioning > Fixed cost per removal (USD, added): 30,000 Decommissioning > USD per metre depth: 600 Decommissioning > Min removals: 1 Decommissioning > Max removals: 25 Decommissioning > Fraction of each structure removed: 0.5 Live solver / Search > Number of scenarios to run: 100 Search > Search algorithm: Random search Search > Random seed: 1,228 | S229: C228_MIX-Region-Shared-Large-Partial.json | T229: 100 | U229: 1228 | V229: 988 | W229: 314 | X229: =ROUND((T229+1)*'Read me'!$C$14/60,1) | Z229: Not started | AJ229: =IF(OR(AH229="",'Submission & QC'!$C$18=""),"",IF(AND(ABS(AH229-'Submission & QC'!$C$18)<=0.0005*ABS('Submission & QC'!$C$18),ABS(AI229-'Submission & QC'!$C$19)<=0.0005*ABS('Submission & QC'!$C$19)),"Pass","Fail"))
... A253: C252 | B253: C | C253: 3 | D253: Mixed | E253: MIX-FL-Shared-Large-Partial | F253: Mixed: install and remove (one shared budget), large install budget ($5-15 M), partial removal / toppling (50%; $30,000 + $600/m), Florida panhandle (east of the Perdido River) | G253: Florida panhandle (east of the Perdido River) | K253: Large: $5-15 M | M253: Partial removal / toppling (50%; $30,000 + $600/m) | P253: Yes | R253: Strategy > Strategy: Mixed: decommission and install Strategy > Shared budget: ticked Installation > Maximum budget per scenario (USD): 15,000,000 Installation > Minimum budget per scenario (USD): 5,000,000 Installation > How budgets are drawn: Uniform Installation > West lon: -87.51 Decommissioning > Removal budget (USD): 5,000,000 Decommissioning > Cost: Depth-based Decommissioning > Fixed cost per removal (USD, added): 30,000 Decommissioning > USD per metre depth: 600 Decommissioning > West lon: -87.51 Decommissioning > Min removals: 1 Decommissioning > Max removals: 25 Decommissioning > Fraction of each structure removed: 0.5 Live solver / Search > Number of scenarios to run: 100 Search > Search algorithm: Random search Search > Random seed: 1,252 | S253: C252_MIX-FL-Shared-Large-Partial.json | T253: 100 | U253: 1252 | V253: 572 | W253: 118 | X253: =ROUND((T253+1)*'Read me'!$C$14/60,1) | Z253: Not started | AJ253: =IF(OR(AH253="",'Submission & QC'!$C$18=""),"",IF(AND(ABS(AH253-'Submission & QC'!$C$18)<=0.0005*ABS('Submission & QC'!$C$18),ABS(AI253-'Submission & QC'!$C$19)<=0.0005*ABS('Submission & QC'!$C$19)),"Pass","Fail"))
A254: D253 | B254: D | C254: 1 | D254: Install | E254: SENS-REF-seed1 | F254: Reference scenario, replicate 1 | Q254: Reference | R254: Strategy > Strategy: Install new structures Installation > Maximum budget per scenario (USD): 5,000,000 Installation > Minimum budget per scenario (USD): 1,000,000 Installation > How budgets are drawn: Uniform Search > Random seed: 1 Live solver / Search > Number of scenarios to run: 100 Search > Search algorithm: Random search | S254: D253_SENS-REF-seed1.json | T254: 100 | U254: 1 | V254: 988 | X254: =ROUND((T254+1)*'Read me'!$C$14/60,1) | Z254: Not started | AJ254: =IF(OR(AH254="",'Submission & QC'!$C$18=""),"",IF(AND(ABS(AH254-'Submission & QC'!$C$18)<=0.0005*ABS('Submission & QC'!$C$18),ABS(AI254-'Submission & QC'!$C$19)<=0.0005*ABS('Submission & QC'!$C$19)),"Pass","Fail"))
A255: D254 | B255: D | C255: 1 | D255: Install | E255: SENS-REF-seed2 | F255: Reference scenario, replicate 2 (different random seed) | Q255: Reference | R255: Strategy > Strategy: Install new structures Installation > Maximum budget per scenario (USD): 5,000,000 Installation > Minimum budget per scenario (USD): 1,000,000 Installation > How budgets are drawn: Uniform Search > Random seed: 2 Live solver / Search > Number of scenarios to run: 100 Search > Search algorithm: Random search | S255: D254_SENS-REF-seed2.json | T255: 100 | U255: 2 | V255: 988 | X255: =ROUND((T255+1)*'Read me'!$C$14/60,1) | Z255: Not started | AJ255: =IF(OR(AH255="",'Submission & QC'!$C$18=""),"",IF(AND(ABS(AH255-'Submission & QC'!$C$18)<=0.0005*ABS('Submission & QC'!$C$18),ABS(AI255-'Submission & QC'!$C$19)<=0.0005*ABS('Submission & QC'!$C$19)),"Pass","Fail"))
A256: D255 | B256: D | C256: 1 | D256: Install | E256: SENS-REF-seed3 | F256: Reference scenario, replicate 3 (different random seed) | Q256: Reference | R256: Strategy > Strategy: Install new structures Installation > Maximum budget per scenario (USD): 5,000,000 Installation > Minimum budget per scenario (USD): 1,000,000 Installation > How budgets are drawn: Uniform Search > Random seed: 3 Live solver / Search > Number of scenarios to run: 100 Search > Search algorithm: Random search | S256: D255_SENS-REF-seed3.json | T256: 100 | U256: 3 | V256: 988 | X256: =ROUND((T256+1)*'Read me'!$C$14/60,1) | Z256: Not started | AJ256: =IF(OR(AH256="",'Submission & QC'!$C$18=""),"",IF(AND(ABS(AH256-'Submission & QC'!$C$18)<=0.0005*ABS('Submission & QC'!$C$18),ABS(AI256-'Submission & QC'!$C$19)<=0.0005*ABS('Submission & QC'!$C$19)),"Pass","Fail"))
A257: D256 | B257: D | C257: 1 | D257: Install | E257: SENS-HALO-250 | F257: Halo radius 250 m (smaller ecological footprint per module) | Q257: Halo radius | R257: Strategy > Strategy: Install new structures Installation > Maximum budget per scenario (USD): 5,000,000 Installation > Minimum budget per scenario (USD): 1,000,000 Installation > How budgets are drawn: Uniform Installation > Halo radius (m): 250 Live solver / Search > Number of scenarios to run: 100 Search > Search algorithm: Random search Search > Random seed: 1,256 | S257: D256_SENS-HALO-250.json | T257: 100 | U257: 1256 | V257: 988 | X257: =ROUND((T257+1)*'Read me'!$C$14/60,1) | Z257: Not started | AJ257: =IF(OR(AH257="",'Submission & QC'!$C$18=""),"",IF(AND(ABS(AH257-'Submission & QC'!$C$18)<=0.0005*ABS('Submission & QC'!$C$18),ABS(AI257-'Submission & QC'!$C$19)<=0.0005*ABS('Submission & QC'!$C$19)),"Pass","Fail"))
A258: D257 | B258: D | C258: 1 | D258: Install | E258: SENS-HALO-1000 | F258: Halo radius 1,000 m (larger ecological footprint per module) | Q258: Halo radius | R258: Strategy > Strategy: Install new structures Installation > Maximum budget per scenario (USD): 5,000,000 Installation > Minimum budget per scenario (USD): 1,000,000 Installation > How budgets are drawn: Uniform Installation > Halo radius (m): 1,000 Live solver / Search > Number of scenarios to run: 100 Search > Search algorithm: Random search Search > Random seed: 1,257 | S258: D257_SENS-HALO-1000.json | T258: 100 | U258: 1257 | V258: 988 | X258: =ROUND((T258+1)*'Read me'!$C$14/60,1) | Z258: Not started | AJ258: =IF(OR(AH258="",'Submission & QC'!$C$18=""),"",IF(AND(ABS(AH258-'Submission & QC'!$C$18)<=0.0005*ABS('Submission & QC'!$C$18),ABS(AI258-'Submission & QC'!$C$19)<=0.0005*ABS('Submission & QC'!$C$19)),"Pass","Fail"))
A259: D258 | B259: D | C259: 2 | D259: Install | E259: SENS-COST-1500 | F259: Module cost $1,500 | Q259: Module cost | R259: Strategy > Strategy: Install new structures Installation > Maximum budget per scenario (USD): 5,000,000 Installation > Minimum budget per scenario (USD): 1,000,000 Installation > How budgets are drawn: Uniform Installation > Cost per module (USD): 1,500 Live solver / Search > Number of scenarios to run: 100 Search > Search algorithm: Random search Search > Random seed: 1,258 | S259: D258_SENS-COST-1500.json | T259: 100 | U259: 1258 | V259: 988 | X259: =ROUND((T259+1)*'Read me'!$C$14/60,1) | Z259: Not started | AJ259: =IF(OR(AH259="",'Submission & QC'!$C$18=""),"",IF(AND(ABS(AH259-'Submission & QC'!$C$18)<=0.0005*ABS('Submission & QC'!$C$18),ABS(AI259-'Submission & QC'!$C$19)<=0.0005*ABS('Submission & QC'!$C$19)),"Pass","Fail"))
A260: D259 | B260: D | C260: 2 | D260: Install | E260: SENS-COST-5000 | F260: Module cost $5,000 | Q260: Module cost | R260: Strategy > Strategy: Install new structures Installation > Maximum budget per scenario (USD): 5,000,000 Installation > Minimum budget per scenario (USD): 1,000,000 Installation > How budgets are drawn: Uniform Installation > Cost per module (USD): 5,000 Live solver / Search > Number of scenarios to run: 100 Search > Search algorithm: Random search Search > Random seed: 1,259 | S260: D259_SENS-COST-5000.json | T260: 100 | U260: 1259 | V260: 988 | X260: =ROUND((T260+1)*'Read me'!$C$14/60,1) | Z260: Not started | AJ260: =IF(OR(AH260="",'Submission & QC'!$C$18=""),"",IF(AND(ABS(AH260-'Submission & QC'!$C$18)<=0.0005*ABS('Submission & QC'!$C$18),ABS(AI260-'Submission & QC'!$C$19)<=0.0005*ABS('Submission & QC'!$C$19)),"Pass","Fail"))
A261: D260 | B261: D | C261: 2 | D261: Install | E261: SENS-DISC-0 | F261: No batch discount | Q261: Batch discount | R261: Strategy > Strategy: Install new structures Installation > Maximum budget per scenario (USD): 5,000,000 Installation > Minimum budget per scenario (USD): 1,000,000 Installation > How budgets are drawn: Uniform Installation > Max batch discount (0-1): 0 Live solver / Search > Number of scenarios to run: 100 Search > Search algorithm: Random search Search > Random seed: 1,260 | S261: D260_SENS-DISC-0.json | T261: 100 | U261: 1260 | V261: 988 | X261: =ROUND((T261+1)*'Read me'!$C$14/60,1) | Z261: Not started | AJ261: =IF(OR(AH261="",'Submission & QC'!$C$18=""),"",IF(AND(ABS(AH261-'Submission & QC'!$C$18)<=0.0005*ABS('Submission & QC'!$C$18),ABS(AI261-'Submission & QC'!$C$19)<=0.0005*ABS('Submission & QC'!$C$19)),"Pass","Fail"))
A262: D261 | B262: D | C262: 2 | D262: Install | E262: SENS-DISC-50 | F262: Batch discount up to 50% | Q262: Batch discount | R262: Strategy > Strategy: Install new structures Installation > Maximum budget per scenario (USD): 5,000,000 Installation > Minimum budget per scenario (USD): 1,000,000 Installation > How budgets are drawn: Uniform Installation > Max batch discount (0-1): 0.5 Live solver / Search > Number of scenarios to run: 100 Search > Search algorithm: Random search Search > Random seed: 1,261 | S262: D261_SENS-DISC-50.json | T262: 100 | U262: 1261 | V262: 988 | X262: =ROUND((T262+1)*'Read me'!$C$14/60,1) | Z262: Not started | AJ262: =IF(OR(AH262="",'Submission & QC'!$C$18=""),"",IF(AND(ABS(AH262-'Submission & QC'!$C$18)<=0.0005*ABS('Submission & QC'!$C$18),ABS(AI262-'Submission & QC'!$C$19)<=0.0005*ABS('Submission & QC'!$C$19)),"Pass","Fail"))
A263: D262 | B263: D | C263: 2 | D263: Install | E263: SENS-DROP-25 | F263: At most 25 modules per drop (many small sites) | Q263: Modules per drop | R263: Strategy > Strategy: Install new structures Installation > Maximum budget per scenario (USD): 5,000,000 Installation > Minimum budget per scenario (USD): 1,000,000 Installation > How budgets are drawn: Uniform Installation > Max modules per drop: 25 Live solver / Search > Number of scenarios to run: 100 Search > Search algorithm: Random search Search > Random seed: 1,262 | S263: D262_SENS-DROP-25.json | T263: 100 | U263: 1262 | V263: 988 | X263: =ROUND((T263+1)*'Read me'!$C$14/60,1) | Z263: Not started | AJ263: =IF(OR(AH263="",'Submission & QC'!$C$18=""),"",IF(AND(ABS(AH263-'Submission & QC'!$C$18)<=0.0005*ABS('Submission & QC'!$C$18),ABS(AI263-'Submission & QC'!$C$19)<=0.0005*ABS('Submission & QC'!$C$19)),"Pass","Fail"))
A264: D263 | B264: D | C264: 2 | D264: Install | E264: SENS-DROP-250 | F264: Up to 250 modules per drop (few large sites) | Q264: Modules per drop | R264: Strategy > Strategy: Install new structures Installation > Maximum budget per scenario (USD): 5,000,000 Installation > Minimum budget per scenario (USD): 1,000,000 Installation > How budgets are drawn: Uniform Installation > Max modules per drop: 250 Live solver / Search > Number of scenarios to run: 100 Search > Search algorithm: Random search Search > Random seed: 1,263 | S264: D263_SENS-DROP-250.json | T264: 100 | U264: 1263 | V264: 988 | X264: =ROUND((T264+1)*'Read me'!$C$14/60,1) | Z264: Not started | AJ264: =IF(OR(AH264="",'Submission & QC'!$C$18=""),"",IF(AND(ABS(AH264-'Submission & QC'!$C$18)<=0.0005*ABS('Submission & QC'!$C$18),ABS(AI264-'Submission & QC'!$C$19)<=0.0005*ABS('Submission & QC'!$C$19)),"Pass","Fail"))
A265: D264 | B265: D | C265: 2 | D265: Install | E265: SENS-FRAC-25 | F265: Reef may cover at most 25% of a cell | Q265: Max reef share of a cell | R265: Strategy > Strategy: Install new structures Installation > Maximum budget per scenario (USD): 5,000,000 Installation > Minimum budget per scenario (USD): 1,000,000 Installation > How budgets are drawn: Uniform Installation > Max reef share of a cell (0-1): 0.25 Live solver / Search > Number of scenarios to run: 100 Search > Search algorithm: Random search Search > Random seed: 1,264 | S265: D264_SENS-FRAC-25.json | T265: 100 | U265: 1264 | V265: 988 | X265: =ROUND((T265+1)*'Read me'!$C$14/60,1) | Z265: Not started | AJ265: =IF(OR(AH265="",'Submission & QC'!$C$18=""),"",IF(AND(ABS(AH265-'Submission & QC'!$C$18)<=0.0005*ABS('Submission & QC'!$C$18),ABS(AI265-'Submission & QC'!$C$19)<=0.0005*ABS('Submission & QC'!$C$19)),"Pass","Fail"))
... A279: D278 | B279: D | C279: 3 | D279: Install | E279: SENS-COVER-one | F279: Each existing structure cell given one module's cover | Q279: Existing structure cover | R279: Strategy > Strategy: Install new structures Installation > Maximum budget per scenario (USD): 5,000,000 Installation > Minimum budget per scenario (USD): 1,000,000 Installation > How budgets are drawn: Uniform Model & run > Cover of each existing structure cell: One module's cover Live solver / Search > Number of scenarios to run: 100 Search > Search algorithm: Random search Search > Random seed: 1,278 | S279: D278_SENS-COVER-one.json | T279: 100 | U279: 1278 | V279: 988 | X279: =ROUND((T279+1)*'Read me'!$C$14/60,1) | Z279: Not started | AJ279: =IF(OR(AH279="",'Submission & QC'!$C$18=""),"",IF(AND(ABS(AH279-'Submission & QC'!$C$18)<=0.0005*ABS('Submission & QC'!$C$18),ABS(AI279-'Submission & QC'!$C$19)<=0.0005*ABS('Submission & QC'!$C$19)),"Pass","Fail"))

Sheet Factors & levels
A1: Block | B1: Factor | C1: Level | D1: Meaning | E1: Setup panel > field: value | F1: Rationale and source
A3: A, C | B3: Zone | C3: Region | D3: Whole model area | E3: (no longitude limits) | F3: Baseline: the full NGoM domain (988 eligible installation cells, 314 existing structure cells).
A4: A, B, C | B4: Zone | C4: AL | D4: Alabama: west of the Perdido River | E4: Installation and/or Decommissioning > East lon: -87.51 | F4: The AL-FL state line (Perdido River, about 87.5 W) coincides with the boundary between grid columns 19 and 20, which is also the edge of the Alabama reef zone used for the existing-reef baseline. Alabama manages large artificial reef zones offshore of Baldwin and Mobile counties (ADCNR).
A5: A, B, C | B5: Zone | C5: FL | D5: Florida panhandle: east of the Perdido River | E5: Installation and/or Decommissioning > West lon: -87.51 | F5: Florida panhandle reef sites (Escambia to Bay counties) permitted under FWC; the source of reeflocations.csv.
A6: A | B6: Depth band | C6: Any | D6: All eligible depths (10-100 m in this grid) | E6: (no depth limits) | F6: Eligible installation cells span 10-100 m (median 36 m).
A7: A | B7: Depth band | C7: Shallow | D7: 10-30 m | E7: Installation > Min depth (m): 10; Max depth (m): 30 | F7: Nearshore permitted reef sites; panhandle permits list depths from about 18 to 300 ft (5.5-91 m). 330 eligible cells.
A8: A | B8: Depth band | C8: Mid | D8: 30-60 m | E8: Installation > Min depth (m): 30; Max depth (m): 60 | F8: Mid-shelf, where most large-area reef sites and red snapper habitat lie. 489 eligible cells.
A9: A | B9: Depth band | C9: Deep | D9: 60-100 m | E9: Installation > Min depth (m): 60; Max depth (m): 100 | F9: Outer shelf; costlier and less accessible to recreational anglers. 202 eligible cells (57 in Alabama).
A10: A | B10: Module type | C10: Std | D10: Standard prefabricated concrete module: $2,500 deployed, 6 m2 footprint, 3 m tall | E10: (defaults) | F10: Deployed costs for prefabricated concrete modules in NW Florida are roughly $2,200-4,500 each (Bay County 2014: $2,200; FWC 2017-21: about $3,200 average for 3,607 modules; Okaloosa 2024: about $4,500). Default of structure_optimization.R.
A11: A | B11: Module type | C11: Large | D11: Large module (super-pyramid class): $12,000, 20 m2, 6 m tall | E11: Installation > Cost per module (USD): 12,000; Footprint (m2): 20; Height (m): 6 | F11: ASSUMPTION to confirm with the coordinator/vendor quotes: larger, taller units cost more per module but add more relief and cover per drop.
A12: A | B12: Layout | C12: Disp | D12: Dispersed: cells chosen without regard to neighbours | E12: Installation > Favour cells next to existing modules: unticked | F12: Default random placement.
A13: A | B13: Layout | C13: Clust | D13: Clustered: favour cells next to existing modules | E13: Installation > Favour cells next to existing modules: ticked; Connectivity bonus: 10 | F13: Tests whether aggregating reef (larger reef complexes, halo overlap) outperforms spreading it.
... A24: D | B24: Sensitivity (one at a time) | C24: see Scenarios D253-D278 | D24: Halo radius, module cost, batch discount, modules per drop, reef share, displacement, habitat avoidance, buffer, exclusions, navigation clearance, depth cost, budget sampling, search algorithm, years averaged, existing-reef baseline, existing cover; plus 3 replicates of the reference | E24: Reference: whole area, any depth, standard module, dispersed, $1-5 M | F24: Halo radius is uncertain: telemetry puts red snapper on average about 26 m (SD 35 m) from artificial reefs, but forage halos extend much further, so 250, 500 (default) and 1,000 m are tested. Navigation clearance: panhandle permits require 40-50 ft (12-15 m) of water over the reef top. The replicates measure run-to-run noise.

Sheet Fixed settings
A1: Setup panel | B1: Field | C1: Value (all scenarios unless a scenario says otherwise) | D1: Note
A3: Model & run | B3: Ecospace model | C3: NGoM / NGoM_forConsole
A4: Model & run | B4: Ecosim / Ecospace scenario index | C4: 1 / 1
A5: Model & run | B5: Run length (years) | C5: 30 | D5: Reef is added at year 10 in the model
A6: Model & run | B6: Use spin-up; Spin-up (years) | C6: ticked; 5
A7: Model & run | B7: Time steps / year | C7: 12
A8: Model & run | B8: Threads | C8: 15 (may be changed for speed; record it) | D8: Performance only
A9: Model & run | B9: Run timeout (s) | C9: 1800
A10: Model & run | B10: Existing reefs | C10: Automatic: from reeflocations.csv | D10: Except D277
A11: Model & run | B11: Cover of each existing structure cell | C11: Automatic | D11: Except D278
A12: Model & run | B12: Pristine habitat maps | C12: auto (Initial Base Mapps)
A13: Model & run | B13: Natural habitat layers | C13: gravel, mud, rock, sand
A14: Installation | B14: Max modules per drop | C14: 100 | D14: Except D262-D263
A15: Installation | B15: Max batch discount | C15: 0.30 | D15: Except D260-D261
A16: Installation | B16: Halo radius (m) | C16: 500 | D16: Except D256-D257
A17: Installation | B17: Max reef share of a cell | C17: 1 | D17: Except D264
A18: Installation | B18: Min water above crest (m) | C18: 6 | D18: Except D270
A19: Installation | B19: Depth cost factor; Reference depth | C19: 0; 30 m | D19: Except D271
A20: Installation | B20: Respect exclusions map | C20: ticked (exclusions.asc) | D20: Except D269
A21: Installation | B21: Buffer from existing structures | C21: 0 | D21: Except D268
A22: Installation | B22: Avoid habitats | C22: none | D22: Except D266-D267
A23: Installation | B23: Natural habitat under new reef | C23: Makes room for the reef | D23: Except D265
A24: Installation | B24: How budgets are drawn | C24: Uniform | D24: Except D272-D273
A25: Decommissioning | B25: Min structures retained; coverage threshold | C25: 0; 0
A26: Objectives | B26: Objectives | C26: RS_Biomass, RS_Catch, Reef_Fish_Biomass, Total_Revenue (max, weight 1) | D26: Re-weighted centrally afterwards
A27: Objectives | B27: Average over the last N years | C27: 5 | D27: Except D275-D276
A28: Economics | B28: Prices, fleets, pounds per tonne | C28: Defaults
A29: Search | B29: Search algorithm | C29: Random search | D29: Except D274

Sheet Objective sets
A1: Objective sets applied afterwards by re-scoring (no extra Ecospace runs)
A2: Every saved run keeps its full Ecospace output, so the analysis lead re-scores all sessions with each set (Live Solver re-score, or ls_update_objectives in R). Contributors always run with Set 1.
A4: Set | B4: Name | C4: Objective | D4: Direction | E4: Weight | F4: Question it answers
A6: 1 | B6: Default (as run) | C6: RS_Biomass | D6: max | E6: 1 | F6: Balanced fishery and stock outcomes.
C7: RS_Catch | D7: max | E7: 1
C8: Reef_Fish_Biomass | D8: max | E8: 1
C9: Total_Revenue | D9: max | E9: 1
A10: 2 | B10: Red snapper fishery | C10: RS_Catch | D10: max | E10: 2 | F10: Where should reef go to maximise red snapper landings?
C11: RS_Biomass | D11: max | E11: 1
C12: Total_Revenue | D12: max | E12: 1
A13: 3 | B13: Conservation / ecosystem | C13: Fed_Biomass | D13: max | E13: 1 | F13: Does reef build stocks and diversity without boosting invasive lionfish?
C14: Biodiversity | D14: max | E14: 1
C15: Lionfish_Biomass | D15: min | E15: 1
C16: RS_Biomass | D16: max | E16: 1
A17: 4 | B17: Economic return | C17: Total_Revenue | D17: max | E17: 2 | F17: Which layouts pay back fastest?
C18: Comm_Revenue | D18: max | E18: 1
A19: 5 | B19: Sector balance | C19: Comm_Catch | D19: max | E19: 1 | F19: Do layouts favour commercial or recreational fleets?
C20: Rec_Catch | D20: max | E20: 1
A21: 6 | B21: Multi-species stocks | C21: FedSp_greater_amberjack_Biomass | D21: max | E21: 1 | F21: Winners and losers among the eight federally managed reef fish.
C22: FedSp_gag_Biomass | D22: max | E22: 1
C23: FedSp_red_grouper_Biomass | D23: max | E23: 1
C24: FedSp_red_snapper_Biomass | D24: max | E24: 1
C25: FedSp_gray_snapper_Biomass | D25: max | E25: 1
C26: FedSp_lane_snapper_Biomass | D26: max | E26: 1
C27: FedSp_gray_triggerfish_Biomass | D27: max | E27: 1
C28: FedSp_vermilion_snapper_Biomass | D28: max | E28: 1

Sheet Submission & QC
A1: Before you start
A2: 1 | B2: Row claimed (name + Status 'Claimed').
A3: 2 | B3: Fresh unzipped package; log shows version ebf8874.
A4: 3 | B4: Console location set; Test mode OFF.
A5: 4 | B5: Scenario configuration loaded from the configs folder; no other setting changed.
A6: 5 | B6: Constraint preview eligible cells match the Scenarios sheet.
A7: 6 | B7: Computer plugged in; sleep and hibernation disabled.
A9: After the session
A10: 1 | B10: Log ends with 'Restored the original maps' and 'Best run: ...'; no warnings about identical outcomes, stale cache or grid mismatch.
A11: 2 | B11: optimization_results.csv has the listed number of runs + 1 (status quo) rows, all finished.
A12: 3 | B12: Status quo RS_Biomass and RS_Catch copied into the row and compared with the reference below.
A13: 4 | B13: Session folder zipped as <ScenarioID>_<Initials>.zip and uploaded; link pasted in the row.
A14: 5 | B14: Row completed: dates, version, runs finished, minutes per run, threads, computer, Status 'Done - uploaded'.
A16: Status quo reference values
B17: The coordinator fills these from the first completed reference run (D253). Every session's Run_0001_Status_Quo must match to 4 significant figures.
B18: RS_Biomass (status quo)
B19: RS_Catch (status quo)

Sheet Progress
A1: Programme progress (updates as the Scenarios sheet is filled in)
A3: Group | B3: Scenarios | C3: Not started | D3: Claimed | E3: Running | F3: Done - uploaded | G3: QC passed | H3: QC failed - rerun | I3: Problem | J3: % done | K3: Hours remaining
A5: All scenarios | B5: =COUNTA(Scenarios!$Z$2:$Z$279) | C5: =COUNTIFS(Scenarios!$Z$2:$Z$279,"Not started") | D5: =COUNTIFS(Scenarios!$Z$2:$Z$279,"Claimed") | E5: =COUNTIFS(Scenarios!$Z$2:$Z$279,"Running") | F5: =COUNTIFS(Scenarios!$Z$2:$Z$279,"Done - uploaded") | G5: =COUNTIFS(Scenarios!$Z$2:$Z$279,"QC passed") | H5: =COUNTIFS(Scenarios!$Z$2:$Z$279,"QC failed - rerun") | I5: =COUNTIFS(Scenarios!$Z$2:$Z$279,"Problem") | J5: =IF(B5=0,0,(F5+G5)/B5) | K5: =ROUND(SUM(Scenarios!$X$2:$X$279)-SUMIFS(Scenarios!$X$2:$X$279,Scenarios!$Z$2:$Z$279,"Done - uploaded")-SUMIFS(Scenarios!$X$2:$X$279,Scenarios!$Z$2:$Z$279,"QC passed"),0)
A6: Block A: installation | B6: =COUNTIFS(Scenarios!$Z$2:$Z$279,"<>zz",Scenarios!$B$2:$B$279,"A") | C6: =COUNTIFS(Scenarios!$Z$2:$Z$279,"Not started",Scenarios!$B$2:$B$279,"A") | D6: =COUNTIFS(Scenarios!$Z$2:$Z$279,"Claimed",Scenarios!$B$2:$B$279,"A") | E6: =COUNTIFS(Scenarios!$Z$2:$Z$279,"Running",Scenarios!$B$2:$B$279,"A") | F6: =COUNTIFS(Scenarios!$Z$2:$Z$279,"Done - uploaded",Scenarios!$B$2:$B$279,"A") | G6: =COUNTIFS(Scenarios!$Z$2:$Z$279,"QC passed",Scenarios!$B$2:$B$279,"A") | H6: =COUNTIFS(Scenarios!$Z$2:$Z$279,"QC failed - rerun",Scenarios!$B$2:$B$279,"A") | I6: =COUNTIFS(Scenarios!$Z$2:$Z$279,"Problem",Scenarios!$B$2:$B$279,"A") | J6: =IF(B6=0,0,(F6+G6)/B6) | K6: =ROUND(SUMIFS(Scenarios!$X$2:$X$279,Scenarios!$B$2:$B$279,"A")-SUMIFS(Scenarios!$X$2:$X$279,Scenarios!$Z$2:$Z$279,"Done - uploaded",Scenarios!$B$2:$B$279,"A")-SUMIFS(Scenarios!$X$2:$X$279,Scenarios!$Z$2:$Z$279,"QC passed",Scenarios!$B$2:$B$279,"A"),0)
A7: Block B: decommissioning | B7: =COUNTIFS(Scenarios!$Z$2:$Z$279,"<>zz",Scenarios!$B$2:$B$279,"B") | C7: =COUNTIFS(Scenarios!$Z$2:$Z$279,"Not started",Scenarios!$B$2:$B$279,"B") | D7: =COUNTIFS(Scenarios!$Z$2:$Z$279,"Claimed",Scenarios!$B$2:$B$279,"B") | E7: =COUNTIFS(Scenarios!$Z$2:$Z$279,"Running",Scenarios!$B$2:$B$279,"B") | F7: =COUNTIFS(Scenarios!$Z$2:$Z$279,"Done - uploaded",Scenarios!$B$2:$B$279,"B") | G7: =COUNTIFS(Scenarios!$Z$2:$Z$279,"QC passed",Scenarios!$B$2:$B$279,"B") | H7: =COUNTIFS(Scenarios!$Z$2:$Z$279,"QC failed - rerun",Scenarios!$B$2:$B$279,"B") | I7: =COUNTIFS(Scenarios!$Z$2:$Z$279,"Problem",Scenarios!$B$2:$B$279,"B") | J7: =IF(B7=0,0,(F7+G7)/B7) | K7: =ROUND(SUMIFS(Scenarios!$X$2:$X$279,Scenarios!$B$2:$B$279,"B")-SUMIFS(Scenarios!$X$2:$X$279,Scenarios!$Z$2:$Z$279,"Done - uploaded",Scenarios!$B$2:$B$279,"B")-SUMIFS(Scenarios!$X$2:$X$279,Scenarios!$Z$2:$Z$279,"QC passed",Scenarios!$B$2:$B$279,"B"),0)
A8: Block C: mixed | B8: =COUNTIFS(Scenarios!$Z$2:$Z$279,"<>zz",Scenarios!$B$2:$B$279,"C") | C8: =COUNTIFS(Scenarios!$Z$2:$Z$279,"Not started",Scenarios!$B$2:$B$279,"C") | D8: =COUNTIFS(Scenarios!$Z$2:$Z$279,"Claimed",Scenarios!$B$2:$B$279,"C") | E8: =COUNTIFS(Scenarios!$Z$2:$Z$279,"Running",Scenarios!$B$2:$B$279,"C") | F8: =COUNTIFS(Scenarios!$Z$2:$Z$279,"Done - uploaded",Scenarios!$B$2:$B$279,"C") | G8: =COUNTIFS(Scenarios!$Z$2:$Z$279,"QC passed",Scenarios!$B$2:$B$279,"C") | H8: =COUNTIFS(Scenarios!$Z$2:$Z$279,"QC failed - rerun",Scenarios!$B$2:$B$279,"C") | I8: =COUNTIFS(Scenarios!$Z$2:$Z$279,"Problem",Scenarios!$B$2:$B$279,"C") | J8: =IF(B8=0,0,(F8+G8)/B8) | K8: =ROUND(SUMIFS(Scenarios!$X$2:$X$279,Scenarios!$B$2:$B$279,"C")-SUMIFS(Scenarios!$X$2:$X$279,Scenarios!$Z$2:$Z$279,"Done - uploaded",Scenarios!$B$2:$B$279,"C")-SUMIFS(Scenarios!$X$2:$X$279,Scenarios!$Z$2:$Z$279,"QC passed",Scenarios!$B$2:$B$279,"C"),0)
A9: Block D: sensitivity | B9: =COUNTIFS(Scenarios!$Z$2:$Z$279,"<>zz",Scenarios!$B$2:$B$279,"D") | C9: =COUNTIFS(Scenarios!$Z$2:$Z$279,"Not started",Scenarios!$B$2:$B$279,"D") | D9: =COUNTIFS(Scenarios!$Z$2:$Z$279,"Claimed",Scenarios!$B$2:$B$279,"D") | E9: =COUNTIFS(Scenarios!$Z$2:$Z$279,"Running",Scenarios!$B$2:$B$279,"D") | F9: =COUNTIFS(Scenarios!$Z$2:$Z$279,"Done - uploaded",Scenarios!$B$2:$B$279,"D") | G9: =COUNTIFS(Scenarios!$Z$2:$Z$279,"QC passed",Scenarios!$B$2:$B$279,"D") | H9: =COUNTIFS(Scenarios!$Z$2:$Z$279,"QC failed - rerun",Scenarios!$B$2:$B$279,"D") | I9: =COUNTIFS(Scenarios!$Z$2:$Z$279,"Problem",Scenarios!$B$2:$B$279,"D") | J9: =IF(B9=0,0,(F9+G9)/B9) | K9: =ROUND(SUMIFS(Scenarios!$X$2:$X$279,Scenarios!$B$2:$B$279,"D")-SUMIFS(Scenarios!$X$2:$X$279,Scenarios!$Z$2:$Z$279,"Done - uploaded",Scenarios!$B$2:$B$279,"D")-SUMIFS(Scenarios!$X$2:$X$279,Scenarios!$Z$2:$Z$279,"QC passed",Scenarios!$B$2:$B$279,"D"),0)
A10: Priority 1 | B10: =COUNTIFS(Scenarios!$Z$2:$Z$279,"<>zz",Scenarios!$C$2:$C$279,1) | C10: =COUNTIFS(Scenarios!$Z$2:$Z$279,"Not started",Scenarios!$C$2:$C$279,1) | D10: =COUNTIFS(Scenarios!$Z$2:$Z$279,"Claimed",Scenarios!$C$2:$C$279,1) | E10: =COUNTIFS(Scenarios!$Z$2:$Z$279,"Running",Scenarios!$C$2:$C$279,1) | F10: =COUNTIFS(Scenarios!$Z$2:$Z$279,"Done - uploaded",Scenarios!$C$2:$C$279,1) | G10: =COUNTIFS(Scenarios!$Z$2:$Z$279,"QC passed",Scenarios!$C$2:$C$279,1) | H10: =COUNTIFS(Scenarios!$Z$2:$Z$279,"QC failed - rerun",Scenarios!$C$2:$C$279,1) | I10: =COUNTIFS(Scenarios!$Z$2:$Z$279,"Problem",Scenarios!$C$2:$C$279,1) | J10: =IF(B10=0,0,(F10+G10)/B10) | K10: =ROUND(SUMIFS(Scenarios!$X$2:$X$279,Scenarios!$C$2:$C$279,1)-SUMIFS(Scenarios!$X$2:$X$279,Scenarios!$Z$2:$Z$279,"Done - uploaded",Scenarios!$C$2:$C$279,1)-SUMIFS(Scenarios!$X$2:$X$279,Scenarios!$Z$2:$Z$279,"QC passed",Scenarios!$C$2:$C$279,1),0)
A11: Priority 2 | B11: =COUNTIFS(Scenarios!$Z$2:$Z$279,"<>zz",Scenarios!$C$2:$C$279,2) | C11: =COUNTIFS(Scenarios!$Z$2:$Z$279,"Not started",Scenarios!$C$2:$C$279,2) | D11: =COUNTIFS(Scenarios!$Z$2:$Z$279,"Claimed",Scenarios!$C$2:$C$279,2) | E11: =COUNTIFS(Scenarios!$Z$2:$Z$279,"Running",Scenarios!$C$2:$C$279,2) | F11: =COUNTIFS(Scenarios!$Z$2:$Z$279,"Done - uploaded",Scenarios!$C$2:$C$279,2) | G11: =COUNTIFS(Scenarios!$Z$2:$Z$279,"QC passed",Scenarios!$C$2:$C$279,2) | H11: =COUNTIFS(Scenarios!$Z$2:$Z$279,"QC failed - rerun",Scenarios!$C$2:$C$279,2) | I11: =COUNTIFS(Scenarios!$Z$2:$Z$279,"Problem",Scenarios!$C$2:$C$279,2) | J11: =IF(B11=0,0,(F11+G11)/B11) | K11: =ROUND(SUMIFS(Scenarios!$X$2:$X$279,Scenarios!$C$2:$C$279,2)-SUMIFS(Scenarios!$X$2:$X$279,Scenarios!$Z$2:$Z$279,"Done - uploaded",Scenarios!$C$2:$C$279,2)-SUMIFS(Scenarios!$X$2:$X$279,Scenarios!$Z$2:$Z$279,"QC passed",Scenarios!$C$2:$C$279,2),0)
A12: Priority 3 | B12: =COUNTIFS(Scenarios!$Z$2:$Z$279,"<>zz",Scenarios!$C$2:$C$279,3) | C12: =COUNTIFS(Scenarios!$Z$2:$Z$279,"Not started",Scenarios!$C$2:$C$279,3) | D12: =COUNTIFS(Scenarios!$Z$2:$Z$279,"Claimed",Scenarios!$C$2:$C$279,3) | E12: =COUNTIFS(Scenarios!$Z$2:$Z$279,"Running",Scenarios!$C$2:$C$279,3) | F12: =COUNTIFS(Scenarios!$Z$2:$Z$279,"Done - uploaded",Scenarios!$C$2:$C$279,3) | G12: =COUNTIFS(Scenarios!$Z$2:$Z$279,"QC passed",Scenarios!$C$2:$C$279,3) | H12: =COUNTIFS(Scenarios!$Z$2:$Z$279,"QC failed - rerun",Scenarios!$C$2:$C$279,3) | I12: =COUNTIFS(Scenarios!$Z$2:$Z$279,"Problem",Scenarios!$C$2:$C$279,3) | J12: =IF(B12=0,0,(F12+G12)/B12) | K12: =ROUND(SUMIFS(Scenarios!$X$2:$X$279,Scenarios!$C$2:$C$279,3)-SUMIFS(Scenarios!$X$2:$X$279,Scenarios!$Z$2:$Z$279,"Done - uploaded",Scenarios!$C$2:$C$279,3)-SUMIFS(Scenarios!$X$2:$X$279,Scenarios!$Z$2:$Z$279,"QC passed",Scenarios!$C$2:$C$279,3),0)

Sheet Sources
A1: Topic | B1: Source | C1: Used for
A3: Live Solver settings | B3: OptimalEcospace repository, R/LiveSolver/solver_engine.R (ls_default_config) and app.R; README; User Guide | C3: Every setting name, default and app label in this workbook
A4: Model geography | B4: Analysis of the NGoM model grid (basemap.asc, exclusions.asc, reeflocations.csv) with the Live Solver in test mode | C4: Eligible cells per zone and depth band; AL-FL boundary at grid column 19/20
A5: Module cost | B5: Bay County, FL artificial reef proposal (2014): https://www.baycountyfl.gov/DocumentCenter/View/459/Bay-Pre-Proposal-2014-001e-Artificial-Reef-Proposal-Presentation-PDF | C5: $2,200 per prefabricated module including deployment
A6: Module cost | B6: FWC, NW Florida artificial reef deployments (NRDA Phase III): https://myfwc.com/news/all-news/artificial-reef-521/ | C6: $11.5 M for 3,607 modules (about $3,200 each)
A7: Module cost | B7: Destin-Fort Walton Beach reef project (2024): https://business.destinchamber.com/news/details/news-release-5-13-2024-4527 | C7: $1.26 M for 279 structures; small-budget band
A8: Module cost | B8: Alabama Wildlife Federation reef brochure: https://www.alabamawildlife.org/uploadedFiles/File/ReefBrochure.pdf | C8: About $10,000 per reef (several modules)
A9: Reef programmes | B9: Artificial reefs of the Gulf of Mexico: a review of Gulf state programs: https://platformresearch.msi.ucsb.edu/node/639 | C9: Context for zones and programme scale
A10: Depth / clearance | B10: USACE Mobile District permits for Florida panhandle large-area reefs: https://www.fws.gov/doiddata/dwh-ar-documents/4008/DWH-ARZ010242.pdf (and DWH-ARZ012580/012581) | C10: Clearance of 40-50 ft over the reef top; depths 18-300 ft
A11: Alabama protocol | B11: Alabama Artificial Reef Construction Protocols (2021): https://www.outdooralabama.com/sites/default/files/PDF%20documents/AL%20Artificial%20Reef%20Construction%20Protocols%202021_12%20%281%29.pdf | C11: Alabama permitting context
A12: Halo / movement | B12: Piraino & Szedlmayer, fine-scale movements of red snapper around artificial reefs (SEDAR74-RD02): https://sedarweb.org/documents/sedar-74-rd02-fine-scale-movements-and-home-ranges-of-red-snapper-around-artificial-reefs-in-the-northern-gulf-of-mexico | C12: Mean distance of about 26 m from reef; motivates the halo sensitivity
A13: Halo / depth | B13: Depth and artificial reef type effects on red snapper (SEDAR74-RD04): https://sedarweb.org/documents/sedar-74-rd04-depth-and-artificial-reef-type-effects-on-size-and-distribution-of-red-snapper-in-the-northern-gulf-of-mexico | C13: Depth bands
... A16: Removal cost | B16: Reef-in-place savings of 30-50%: https://internationalfinance.com/magazine/energy-magazine/breathing-new-life-into-oil-and-gas-reserves/ | C16: Partial removal at 60% of full cost
